{
  "run_timestamp": "2026-06-12T12:47:09.316104-04:00",
  "mode": "live",
  "strategy_mode": "daily",
  "equity": 28419.89,
  "last_equity": 28419.89,
  "buying_power": 113679.56,
  "vix": 22.59,
  "drawdown_pct": 0.1,
  "peak_equity": 28448.78,
  "kill_switch_active": false,
  "positions": [],
  "position_details": [],
  "signals": [
    {
      "timestamp": "2026-06-12T12:47:09.316104-04:00",
      "strategy": "rsi_macd_combo",
      "strategy_type": "daily",
      "vix_type": "COMBO",
      "symbol": "SPY",
      "signal": "hold",
      "price": 740.94,
      "atr": 10.9482,
      "qty": 0,
      "stop_price": null,
      "tp_price": null,
      "executed": false,
      "skip_reason": "no_signal",
      "order_id": null,
      "vix": 22.59,
      "vix_reason": "vix_reduced_to_50pct (22.6 >= 20)",
      "indicators": {
        "rsi": 52.47,
        "macd": 3.7186,
        "macd_sig": 7.386,
        "macd_hist": -3.6674
      }
    },
    {
      "timestamp": "2026-06-12T12:47:09.316104-04:00",
      "strategy": "rsi_macd_combo",
      "strategy_type": "daily",
      "vix_type": "COMBO",
      "symbol": "QQQ",
      "signal": "hold",
      "price": 720.66,
      "atr": 17.4929,
      "qty": 0,
      "stop_price": null,
      "tp_price": null,
      "executed": false,
      "skip_reason": "no_signal",
      "order_id": null,
      "vix": 22.59,
      "vix_reason": "vix_reduced_to_50pct (22.6 >= 20)",
      "indicators": {
        "rsi": 55.02,
        "macd": 8.2503,
        "macd_sig": 13.5948,
        "macd_hist": -5.3445
      }
    },
    {
      "timestamp": "2026-06-12T12:47:09.316104-04:00",
      "strategy": "rsi_macd_combo",
      "strategy_type": "daily",
      "vix_type": "COMBO",
      "symbol": "IWM",
      "signal": "hold",
      "price": 293.86,
      "atr": 6.7917,
      "qty": 0,
      "stop_price": null,
      "tp_price": null,
      "executed": false,
      "skip_reason": "no_signal",
      "order_id": null,
      "vix": 22.59,
      "vix_reason": "vix_reduced_to_50pct (22.6 >= 20)",
      "indicators": {
        "rsi": 60.58,
        "macd": 2.9764,
        "macd_sig": 3.3041,
        "macd_hist": -0.3278
      }
    },
    {
      "timestamp": "2026-06-12T12:47:09.316104-04:00",
      "strategy": "rsi_macd_combo",
      "strategy_type": "daily",
      "vix_type": "COMBO",
      "symbol": "GLD",
      "signal": "hold",
      "price": 386.68,
      "atr": 9.1899,
      "qty": 0,
      "stop_price": null,
      "tp_price": null,
      "executed": false,
      "skip_reason": "no_signal",
      "order_id": null,
      "vix": 22.59,
      "vix_reason": "vix_reduced_to_50pct (22.6 >= 20)",
      "indicators": {
        "rsi": 35.14,
        "macd": -10.4048,
        "macd_sig": -7.9603,
        "macd_hist": -2.4445
      }
    },
    {
      "timestamp": "2026-06-12T12:47:09.316104-04:00",
      "strategy": "rsi_macd_combo",
      "strategy_type": "daily",
      "vix_type": "COMBO",
      "symbol": "XLK",
      "signal": "hold",
      "price": 184.93,
      "atr": 6.4307,
      "qty": 0,
      "stop_price": null,
      "tp_price": null,
      "executed": false,
      "skip_reason": "no_signal",
      "order_id": null,
      "vix": 22.59,
      "vix_reason": "vix_reduced_to_50pct (22.6 >= 20)",
      "indicators": {
        "rsi": 55.87,
        "macd": 4.236,
        "macd_sig": 6.1577,
        "macd_hist": -1.9217
      }
    },
    {
      "timestamp": "2026-06-12T12:47:09.316104-04:00",
      "strategy": "rsi_macd_combo",
      "strategy_type": "daily",
      "vix_type": "COMBO",
      "symbol": "XLE",
      "signal": "hold",
      "price": 57.86,
      "atr": 1.419,
      "qty": 0,
      "stop_price": null,
      "tp_price": null,
      "executed": false,
      "skip_reason": "no_signal",
      "order_id": null,
      "vix": 22.59,
      "vix_reason": "vix_reduced_to_50pct (22.6 >= 20)",
      "indicators": {
        "rsi": 49.49,
        "macd": -0.0839,
        "macd_sig": -0.0148,
        "macd_hist": -0.0692
      }
    },
    {
      "timestamp": "2026-06-12T12:47:09.316104-04:00",
      "strategy": "rsi_macd_combo",
      "strategy_type": "daily",
      "vix_type": "COMBO",
      "symbol": "XLF",
      "signal": "hold",
      "price": 53.25,
      "atr": 0.7084,
      "qty": 0,
      "stop_price": null,
      "tp_price": null,
      "executed": false,
      "skip_reason": "no_signal",
      "order_id": null,
      "vix": 22.59,
      "vix_reason": "vix_reduced_to_50pct (22.6 >= 20)",
      "indicators": {
        "rsi": 64.5,
        "macd": 0.3217,
        "macd_sig": 0.176,
        "macd_hist": 0.1457
      }
    },
    {
      "timestamp": "2026-06-12T12:47:09.316104-04:00",
      "strategy": "rsi_macd_combo",
      "strategy_type": "daily",
      "vix_type": "COMBO",
      "symbol": "ARM",
      "signal": "hold",
      "price": 370.89,
      "atr": 37.9369,
      "qty": 0,
      "stop_price": null,
      "tp_price": null,
      "executed": false,
      "skip_reason": "no_signal",
      "order_id": null,
      "vix": 22.59,
      "vix_reason": "vix_reduced_to_50pct (22.6 >= 20)",
      "indicators": {
        "rsi": 62.5,
        "macd": 33.8402,
        "macd_sig": 38.899,
        "macd_hist": -5.0588
      }
    },
    {
      "timestamp": "2026-06-12T12:47:09.316104-04:00",
      "strategy": "rsi_macd_combo",
      "strategy_type": "daily",
      "vix_type": "COMBO",
      "symbol": "MRVL",
      "signal": "hold",
      "price": 284.12,
      "atr": 31.2639,
      "qty": 0,
      "stop_price": null,
      "tp_price": null,
      "executed": false,
      "skip_reason": "no_signal",
      "order_id": null,
      "vix": 22.59,
      "vix_reason": "vix_reduced_to_50pct (22.6 >= 20)",
      "indicators": {
        "rsi": 63.91,
        "macd": 30.9919,
        "macd_sig": 29.4386,
        "macd_hist": 1.5533
      }
    },
    {
      "timestamp": "2026-06-12T12:47:09.316104-04:00",
      "strategy": "rsi_macd_combo",
      "strategy_type": "daily",
      "vix_type": "COMBO",
      "symbol": "MU",
      "signal": "hold",
      "price": 995.54,
      "atr": 82.5544,
      "qty": 0,
      "stop_price": null,
      "tp_price": null,
      "executed": false,
      "skip_reason": "no_signal",
      "order_id": null,
      "vix": 22.59,
      "vix_reason": "vix_reduced_to_50pct (22.6 >= 20)",
      "indicators": {
        "rsi": 62.15,
        "macd": 85.273,
        "macd_sig": 95.5674,
        "macd_hist": -10.2943
      }
    },
    {
      "timestamp": "2026-06-12T12:47:09.316104-04:00",
      "strategy": "rsi_macd_combo",
      "strategy_type": "daily",
      "vix_type": "COMBO",
      "symbol": "AMD",
      "signal": "hold",
      "price": 511.15,
      "atr": 35.1847,
      "qty": 0,
      "stop_price": null,
      "tp_price": null,
      "executed": false,
      "skip_reason": "no_signal",
      "order_id": null,
      "vix": 22.59,
      "vix_reason": "vix_reduced_to_50pct (22.6 >= 20)",
      "indicators": {
        "rsi": 60.41,
        "macd": 28.4617,
        "macd_sig": 36.653,
        "macd_hist": -8.1913
      }
    },
    {
      "timestamp": "2026-06-12T12:47:09.316104-04:00",
      "strategy": "rsi_macd_combo",
      "strategy_type": "daily",
      "vix_type": "COMBO",
      "symbol": "DDOG",
      "signal": "hold",
      "price": 231.7,
      "atr": 13.1927,
      "qty": 0,
      "stop_price": null,
      "tp_price": null,
      "executed": false,
      "skip_reason": "no_signal",
      "order_id": null,
      "vix": 22.59,
      "vix_reason": "vix_reduced_to_50pct (22.6 >= 20)",
      "indicators": {
        "rsi": 58.7,
        "macd": 15.5007,
        "macd_sig": 20.3131,
        "macd_hist": -4.8124
      }
    },
    {
      "timestamp": "2026-06-12T12:47:09.316104-04:00",
      "strategy": "rsi_macd_combo",
      "strategy_type": "daily",
      "vix_type": "COMBO",
      "symbol": "INTC",
      "signal": "hold",
      "price": 124.61,
      "atr": 10.0315,
      "qty": 0,
      "stop_price": null,
      "tp_price": null,
      "executed": false,
      "skip_reason": "no_signal",
      "order_id": null,
      "vix": 22.59,
      "vix_reason": "vix_reduced_to_50pct (22.6 >= 20)",
      "indicators": {
        "rsi": 62.4,
        "macd": 4.2092,
        "macd_sig": 5.1997,
        "macd_hist": -0.9905
      }
    },
    {
      "timestamp": "2026-06-12T12:47:09.316104-04:00",
      "strategy": "rsi_macd_combo",
      "strategy_type": "daily",
      "vix_type": "COMBO",
      "symbol": "PANW",
      "signal": "hold",
      "price": 279.78,
      "atr": 13.6913,
      "qty": 0,
      "stop_price": null,
      "tp_price": null,
      "executed": false,
      "skip_reason": "no_signal",
      "order_id": null,
      "vix": 22.59,
      "vix_reason": "vix_reduced_to_50pct (22.6 >= 20)",
      "indicators": {
        "rsi": 64.91,
        "macd": 17.2494,
        "macd_sig": 20.0109,
        "macd_hist": -2.7615
      }
    },
    {
      "timestamp": "2026-06-12T12:47:09.316104-04:00",
      "strategy": "rsi_macd_combo",
      "strategy_type": "daily",
      "vix_type": "COMBO",
      "symbol": "RKLB",
      "signal": "hold",
      "price": 106.98,
      "atr": 12.155,
      "qty": 0,
      "stop_price": null,
      "tp_price": null,
      "executed": false,
      "skip_reason": "no_signal",
      "order_id": null,
      "vix": 22.59,
      "vix_reason": "vix_reduced_to_50pct (22.6 >= 20)",
      "indicators": {
        "rsi": 45.84,
        "macd": 1.2621,
        "macd_sig": 5.6699,
        "macd_hist": -4.4078
      }
    },
    {
      "timestamp": "2026-06-12T12:47:09.316104-04:00",
      "strategy": "rsi_macd_combo",
      "strategy_type": "daily",
      "vix_type": "COMBO",
      "symbol": "SNOW",
      "signal": "hold",
      "price": 237.04,
      "atr": 14.4445,
      "qty": 0,
      "stop_price": null,
      "tp_price": null,
      "executed": false,
      "skip_reason": "no_signal",
      "order_id": null,
      "vix": 22.59,
      "vix_reason": "vix_reduced_to_50pct (22.6 >= 20)",
      "indicators": {
        "rsi": 64.15,
        "macd": 21.9276,
        "macd_sig": 22.4918,
        "macd_hist": -0.5642
      }
    },
    {
      "timestamp": "2026-06-12T12:47:09.316104-04:00",
      "strategy": "rsi_macd_combo",
      "strategy_type": "daily",
      "vix_type": "COMBO",
      "symbol": "IONQ",
      "signal": "hold",
      "price": 58.21,
      "atr": 5.9636,
      "qty": 0,
      "stop_price": null,
      "tp_price": null,
      "executed": false,
      "skip_reason": "no_signal",
      "order_id": null,
      "vix": 22.59,
      "vix_reason": "vix_reduced_to_50pct (22.6 >= 20)",
      "indicators": {
        "rsi": 50.45,
        "macd": 2.343,
        "macd_sig": 4.0907,
        "macd_hist": -1.7476
      }
    },
    {
      "timestamp": "2026-06-12T12:47:09.316104-04:00",
      "strategy": "rsi_macd_combo",
      "strategy_type": "daily",
      "vix_type": "COMBO",
      "symbol": "QCOM",
      "signal": "hold",
      "price": 213.3,
      "atr": 17.4967,
      "qty": 0,
      "stop_price": null,
      "tp_price": null,
      "executed": false,
      "skip_reason": "no_signal",
      "order_id": null,
      "vix": 22.59,
      "vix_reason": "vix_reduced_to_50pct (22.6 >= 20)",
      "indicators": {
        "rsi": 51.1,
        "macd": 5.6456,
        "macd_sig": 12.0643,
        "macd_hist": -6.4187
      }
    },
    {
      "timestamp": "2026-06-12T12:47:09.316104-04:00",
      "strategy": "rsi_macd_combo",
      "strategy_type": "daily",
      "vix_type": "COMBO",
      "symbol": "SMCI",
      "signal": "hold",
      "price": 30.71,
      "atr": 4.5214,
      "qty": 0,
      "stop_price": null,
      "tp_price": null,
      "executed": false,
      "skip_reason": "no_signal",
      "order_id": null,
      "vix": 22.59,
      "vix_reason": "vix_reduced_to_50pct (22.6 >= 20)",
      "indicators": {
        "rsi": 41.39,
        "macd": 0.8801,
        "macd_sig": 2.7082,
        "macd_hist": -1.8281
      }
    },
    {
      "timestamp": "2026-06-12T12:47:09.316104-04:00",
      "strategy": "rsi_macd_combo",
      "strategy_type": "daily",
      "vix_type": "COMBO",
      "symbol": "SMH",
      "signal": "hold",
      "price": 620.8,
      "atr": 31.6151,
      "qty": 0,
      "stop_price": null,
      "tp_price": null,
      "executed": false,
      "skip_reason": "no_signal",
      "order_id": null,
      "vix": 22.59,
      "vix_reason": "vix_reduced_to_50pct (22.6 >= 20)",
      "indicators": {
        "rsi": 60.7,
        "macd": 20.9904,
        "macd_sig": 25.0693,
        "macd_hist": -4.079
      }
    },
    {
      "timestamp": "2026-06-12T12:47:09.316104-04:00",
      "strategy": "rsi_macd_combo",
      "strategy_type": "daily",
      "vix_type": "COMBO",
      "symbol": "ORCL",
      "signal": "hold",
      "price": 182.54,
      "atr": 15.2026,
      "qty": 0,
      "stop_price": null,
      "tp_price": null,
      "executed": false,
      "skip_reason": "no_signal",
      "order_id": null,
      "vix": 22.59,
      "vix_reason": "vix_reduced_to_50pct (22.6 >= 20)",
      "indicators": {
        "rsi": 41.44,
        "macd": 3.8908,
        "macd_sig": 9.2165,
        "macd_hist": -5.3257
      }
    },
    {
      "timestamp": "2026-06-12T12:47:09.316104-04:00",
      "strategy": "rsi_macd_combo",
      "strategy_type": "daily",
      "vix_type": "COMBO",
      "symbol": "TXN",
      "signal": "hold",
      "price": 301.0,
      "atr": 12.9644,
      "qty": 0,
      "stop_price": null,
      "tp_price": null,
      "executed": false,
      "skip_reason": "no_signal",
      "order_id": null,
      "vix": 22.59,
      "vix_reason": "vix_reduced_to_50pct (22.6 >= 20)",
      "indicators": {
        "rsi": 54.79,
        "macd": 4.3536,
        "macd_sig": 8.0357,
        "macd_hist": -3.6821
      }
    },
    {
      "timestamp": "2026-06-12T12:47:09.316104-04:00",
      "strategy": "rsi_macd_combo",
      "strategy_type": "daily",
      "vix_type": "COMBO",
      "symbol": "XLY",
      "signal": "hold",
      "price": 115.64,
      "atr": 2.2368,
      "qty": 0,
      "stop_price": null,
      "tp_price": null,
      "executed": false,
      "skip_reason": "no_signal",
      "order_id": null,
      "vix": 22.59,
      "vix_reason": "vix_reduced_to_50pct (22.6 >= 20)",
      "indicators": {
        "rsi": 45.45,
        "macd": -0.6042,
        "macd_sig": -0.1558,
        "macd_hist": -0.4484
      }
    },
    {
      "timestamp": "2026-06-12T12:47:09.316104-04:00",
      "strategy": "rsi_macd_combo",
      "strategy_type": "daily",
      "vix_type": "COMBO",
      "symbol": "CVX",
      "signal": "hold",
      "price": 187.7,
      "atr": 4.294,
      "qty": 0,
      "stop_price": null,
      "tp_price": null,
      "executed": false,
      "skip_reason": "no_signal",
      "order_id": null,
      "vix": 22.59,
      "vix_reason": "vix_reduced_to_50pct (22.6 >= 20)",
      "indicators": {
        "rsi": 49.45,
        "macd": -0.3966,
        "macd_sig": -0.5355,
        "macd_hist": 0.1389
      }
    },
    {
      "timestamp": "2026-06-12T12:47:09.316104-04:00",
      "strategy": "rsi_macd_combo",
      "strategy_type": "daily",
      "vix_type": "COMBO",
      "symbol": "COP",
      "signal": "hold",
      "price": 117.89,
      "atr": 3.6947,
      "qty": 0,
      "stop_price": null,
      "tp_price": null,
      "executed": false,
      "skip_reason": "no_signal",
      "order_id": null,
      "vix": 22.59,
      "vix_reason": "vix_reduced_to_50pct (22.6 >= 20)",
      "indicators": {
        "rsi": 48.6,
        "macd": -0.8288,
        "macd_sig": -0.9614,
        "macd_hist": 0.1326
      }
    },
    {
      "timestamp": "2026-06-12T12:47:09.316104-04:00",
      "strategy": "rsi_macd_combo",
      "strategy_type": "daily",
      "vix_type": "COMBO",
      "symbol": "SCHW",
      "signal": "hold",
      "price": 91.05,
      "atr": 2.1074,
      "qty": 0,
      "stop_price": null,
      "tp_price": null,
      "executed": false,
      "skip_reason": "no_signal",
      "order_id": null,
      "vix": 22.59,
      "vix_reason": "vix_reduced_to_50pct (22.6 >= 20)",
      "indicators": {
        "rsi": 55.41,
        "macd": -0.4542,
        "macd_sig": -0.8535,
        "macd_hist": 0.3993
      }
    },
    {
      "timestamp": "2026-06-12T12:47:09.316104-04:00",
      "strategy": "rsi_macd_combo",
      "strategy_type": "daily",
      "vix_type": "COMBO",
      "symbol": "V",
      "signal": "hold",
      "price": 323.83,
      "atr": 6.8306,
      "qty": 0,
      "stop_price": null,
      "tp_price": null,
      "executed": false,
      "skip_reason": "no_signal",
      "order_id": null,
      "vix": 22.59,
      "vix_reason": "vix_reduced_to_50pct (22.6 >= 20)",
      "indicators": {
        "rsi": 51.77,
        "macd": 0.1843,
        "macd_sig": 0.7409,
        "macd_hist": -0.5566
      }
    },
    {
      "timestamp": "2026-06-12T12:47:09.316104-04:00",
      "strategy": "rsi_macd_combo",
      "strategy_type": "daily",
      "vix_type": "COMBO",
      "symbol": "BAC",
      "signal": "hold",
      "price": 55.66,
      "atr": 1.1121,
      "qty": 0,
      "stop_price": null,
      "tp_price": null,
      "executed": false,
      "skip_reason": "no_signal",
      "order_id": null,
      "vix": 22.59,
      "vix_reason": "vix_reduced_to_50pct (22.6 >= 20)",
      "indicators": {
        "rsi": 70.44,
        "macd": 0.9091,
        "macd_sig": 0.5141,
        "macd_hist": 0.395
      }
    },
    {
      "timestamp": "2026-06-12T12:47:09.316104-04:00",
      "strategy": "rsi_macd_combo",
      "strategy_type": "daily",
      "vix_type": "COMBO",
      "symbol": "XLV",
      "signal": "hold",
      "price": 153.86,
      "atr": 2.3209,
      "qty": 0,
      "stop_price": null,
      "tp_price": null,
      "executed": false,
      "skip_reason": "no_signal",
      "order_id": null,
      "vix": 22.59,
      "vix_reason": "vix_reduced_to_50pct (22.6 >= 20)",
      "indicators": {
        "rsi": 62.42,
        "macd": 1.8882,
        "macd_sig": 1.3685,
        "macd_hist": 0.5197
      }
    },
    {
      "timestamp": "2026-06-12T12:47:09.316104-04:00",
      "strategy": "rsi_macd_combo",
      "strategy_type": "daily",
      "vix_type": "COMBO",
      "symbol": "XOM",
      "signal": "hold",
      "price": 147.92,
      "atr": 3.8585,
      "qty": 0,
      "stop_price": null,
      "tp_price": null,
      "executed": false,
      "skip_reason": "no_signal",
      "order_id": null,
      "vix": 22.59,
      "vix_reason": "vix_reduced_to_50pct (22.6 >= 20)",
      "indicators": {
        "rsi": 44.95,
        "macd": -1.0941,
        "macd_sig": -0.7908,
        "macd_hist": -0.3032
      }
    },
    {
      "timestamp": "2026-06-12T12:47:09.316104-04:00",
      "strategy": "macd_crossover",
      "strategy_type": "daily",
      "vix_type": "TREND",
      "symbol": "SPY",
      "signal": "hold",
      "price": 740.94,
      "atr": 10.9482,
      "qty": 0,
      "stop_price": null,
      "tp_price": null,
      "executed": false,
      "skip_reason": "no_signal",
      "order_id": null,
      "vix": 22.59,
      "vix_reason": "vix_reduced_to_50pct (22.6 >= 20)",
      "indicators": {
        "macd": 3.7186,
        "macd_sig": 7.386,
        "macd_hist": -3.6674
      }
    },
    {
      "timestamp": "2026-06-12T12:47:09.316104-04:00",
      "strategy": "macd_crossover",
      "strategy_type": "daily",
      "vix_type": "TREND",
      "symbol": "QQQ",
      "signal": "hold",
      "price": 720.66,
      "atr": 17.4929,
      "qty": 0,
      "stop_price": null,
      "tp_price": null,
      "executed": false,
      "skip_reason": "no_signal",
      "order_id": null,
      "vix": 22.59,
      "vix_reason": "vix_reduced_to_50pct (22.6 >= 20)",
      "indicators": {
        "macd": 8.2503,
        "macd_sig": 13.5948,
        "macd_hist": -5.3445
      }
    },
    {
      "timestamp": "2026-06-12T12:47:09.316104-04:00",
      "strategy": "macd_crossover",
      "strategy_type": "daily",
      "vix_type": "TREND",
      "symbol": "IWM",
      "signal": "hold",
      "price": 293.86,
      "atr": 6.7917,
      "qty": 0,
      "stop_price": null,
      "tp_price": null,
      "executed": false,
      "skip_reason": "no_signal",
      "order_id": null,
      "vix": 22.59,
      "vix_reason": "vix_reduced_to_50pct (22.6 >= 20)",
      "indicators": {
        "macd": 2.9764,
        "macd_sig": 3.3041,
        "macd_hist": -0.3278
      }
    },
    {
      "timestamp": "2026-06-12T12:47:09.316104-04:00",
      "strategy": "macd_crossover",
      "strategy_type": "daily",
      "vix_type": "TREND",
      "symbol": "GLD",
      "signal": "hold",
      "price": 386.68,
      "atr": 9.1899,
      "qty": 0,
      "stop_price": null,
      "tp_price": null,
      "executed": false,
      "skip_reason": "no_signal",
      "order_id": null,
      "vix": 22.59,
      "vix_reason": "vix_reduced_to_50pct (22.6 >= 20)",
      "indicators": {
        "macd": -10.4048,
        "macd_sig": -7.9603,
        "macd_hist": -2.4445
      }
    },
    {
      "timestamp": "2026-06-12T12:47:09.316104-04:00",
      "strategy": "macd_crossover",
      "strategy_type": "daily",
      "vix_type": "TREND",
      "symbol": "XLK",
      "signal": "hold",
      "price": 184.93,
      "atr": 6.4307,
      "qty": 0,
      "stop_price": null,
      "tp_price": null,
      "executed": false,
      "skip_reason": "no_signal",
      "order_id": null,
      "vix": 22.59,
      "vix_reason": "vix_reduced_to_50pct (22.6 >= 20)",
      "indicators": {
        "macd": 4.236,
        "macd_sig": 6.1577,
        "macd_hist": -1.9217
      }
    },
    {
      "timestamp": "2026-06-12T12:47:09.316104-04:00",
      "strategy": "macd_crossover",
      "strategy_type": "daily",
      "vix_type": "TREND",
      "symbol": "XLE",
      "signal": "hold",
      "price": 57.86,
      "atr": 1.419,
      "qty": 0,
      "stop_price": null,
      "tp_price": null,
      "executed": false,
      "skip_reason": "no_signal",
      "order_id": null,
      "vix": 22.59,
      "vix_reason": "vix_reduced_to_50pct (22.6 >= 20)",
      "indicators": {
        "macd": -0.0839,
        "macd_sig": -0.0148,
        "macd_hist": -0.0692
      }
    },
    {
      "timestamp": "2026-06-12T12:47:09.316104-04:00",
      "strategy": "macd_crossover",
      "strategy_type": "daily",
      "vix_type": "TREND",
      "symbol": "XLF",
      "signal": "hold",
      "price": 53.25,
      "atr": 0.7084,
      "qty": 0,
      "stop_price": null,
      "tp_price": null,
      "executed": false,
      "skip_reason": "no_signal",
      "order_id": null,
      "vix": 22.59,
      "vix_reason": "vix_reduced_to_50pct (22.6 >= 20)",
      "indicators": {
        "macd": 0.3217,
        "macd_sig": 0.176,
        "macd_hist": 0.1457
      }
    },
    {
      "timestamp": "2026-06-12T12:47:09.316104-04:00",
      "strategy": "macd_crossover",
      "strategy_type": "daily",
      "vix_type": "TREND",
      "symbol": "ARM",
      "signal": "hold",
      "price": 370.89,
      "atr": 37.9369,
      "qty": 0,
      "stop_price": null,
      "tp_price": null,
      "executed": false,
      "skip_reason": "no_signal",
      "order_id": null,
      "vix": 22.59,
      "vix_reason": "vix_reduced_to_50pct (22.6 >= 20)",
      "indicators": {
        "macd": 33.8402,
        "macd_sig": 38.899,
        "macd_hist": -5.0588
      }
    },
    {
      "timestamp": "2026-06-12T12:47:09.316104-04:00",
      "strategy": "macd_crossover",
      "strategy_type": "daily",
      "vix_type": "TREND",
      "symbol": "MRVL",
      "signal": "hold",
      "price": 284.12,
      "atr": 31.2639,
      "qty": 0,
      "stop_price": null,
      "tp_price": null,
      "executed": false,
      "skip_reason": "no_signal",
      "order_id": null,
      "vix": 22.59,
      "vix_reason": "vix_reduced_to_50pct (22.6 >= 20)",
      "indicators": {
        "macd": 30.9919,
        "macd_sig": 29.4386,
        "macd_hist": 1.5533
      }
    },
    {
      "timestamp": "2026-06-12T12:47:09.316104-04:00",
      "strategy": "macd_crossover",
      "strategy_type": "daily",
      "vix_type": "TREND",
      "symbol": "MU",
      "signal": "hold",
      "price": 995.54,
      "atr": 82.5544,
      "qty": 0,
      "stop_price": null,
      "tp_price": null,
      "executed": false,
      "skip_reason": "no_signal",
      "order_id": null,
      "vix": 22.59,
      "vix_reason": "vix_reduced_to_50pct (22.6 >= 20)",
      "indicators": {
        "macd": 85.273,
        "macd_sig": 95.5674,
        "macd_hist": -10.2943
      }
    },
    {
      "timestamp": "2026-06-12T12:47:09.316104-04:00",
      "strategy": "macd_crossover",
      "strategy_type": "daily",
      "vix_type": "TREND",
      "symbol": "AMD",
      "signal": "hold",
      "price": 511.15,
      "atr": 35.1847,
      "qty": 0,
      "stop_price": null,
      "tp_price": null,
      "executed": false,
      "skip_reason": "no_signal",
      "order_id": null,
      "vix": 22.59,
      "vix_reason": "vix_reduced_to_50pct (22.6 >= 20)",
      "indicators": {
        "macd": 28.4617,
        "macd_sig": 36.653,
        "macd_hist": -8.1913
      }
    },
    {
      "timestamp": "2026-06-12T12:47:09.316104-04:00",
      "strategy": "macd_crossover",
      "strategy_type": "daily",
      "vix_type": "TREND",
      "symbol": "DDOG",
      "signal": "hold",
      "price": 231.7,
      "atr": 13.1927,
      "qty": 0,
      "stop_price": null,
      "tp_price": null,
      "executed": false,
      "skip_reason": "no_signal",
      "order_id": null,
      "vix": 22.59,
      "vix_reason": "vix_reduced_to_50pct (22.6 >= 20)",
      "indicators": {
        "macd": 15.5007,
        "macd_sig": 20.3131,
        "macd_hist": -4.8124
      }
    },
    {
      "timestamp": "2026-06-12T12:47:09.316104-04:00",
      "strategy": "macd_crossover",
      "strategy_type": "daily",
      "vix_type": "TREND",
      "symbol": "INTC",
      "signal": "hold",
      "price": 124.61,
      "atr": 10.0315,
      "qty": 0,
      "stop_price": null,
      "tp_price": null,
      "executed": false,
      "skip_reason": "no_signal",
      "order_id": null,
      "vix": 22.59,
      "vix_reason": "vix_reduced_to_50pct (22.6 >= 20)",
      "indicators": {
        "macd": 4.2092,
        "macd_sig": 5.1997,
        "macd_hist": -0.9905
      }
    },
    {
      "timestamp": "2026-06-12T12:47:09.316104-04:00",
      "strategy": "macd_crossover",
      "strategy_type": "daily",
      "vix_type": "TREND",
      "symbol": "PANW",
      "signal": "hold",
      "price": 279.78,
      "atr": 13.6913,
      "qty": 0,
      "stop_price": null,
      "tp_price": null,
      "executed": false,
      "skip_reason": "no_signal",
      "order_id": null,
      "vix": 22.59,
      "vix_reason": "vix_reduced_to_50pct (22.6 >= 20)",
      "indicators": {
        "macd": 17.2494,
        "macd_sig": 20.0109,
        "macd_hist": -2.7615
      }
    },
    {
      "timestamp": "2026-06-12T12:47:09.316104-04:00",
      "strategy": "macd_crossover",
      "strategy_type": "daily",
      "vix_type": "TREND",
      "symbol": "RKLB",
      "signal": "hold",
      "price": 106.98,
      "atr": 12.155,
      "qty": 0,
      "stop_price": null,
      "tp_price": null,
      "executed": false,
      "skip_reason": "no_signal",
      "order_id": null,
      "vix": 22.59,
      "vix_reason": "vix_reduced_to_50pct (22.6 >= 20)",
      "indicators": {
        "macd": 1.2621,
        "macd_sig": 5.6699,
        "macd_hist": -4.4078
      }
    },
    {
      "timestamp": "2026-06-12T12:47:09.316104-04:00",
      "strategy": "macd_crossover",
      "strategy_type": "daily",
      "vix_type": "TREND",
      "symbol": "SNOW",
      "signal": "sell",
      "price": 237.04,
      "atr": 14.4445,
      "qty": 0,
      "stop_price": null,
      "tp_price": null,
      "executed": false,
      "skip_reason": "no_position_to_sell",
      "order_id": null,
      "vix": 22.59,
      "vix_reason": "vix_reduced_to_50pct (22.6 >= 20)",
      "indicators": {
        "macd": 21.9276,
        "macd_sig": 22.4918,
        "macd_hist": -0.5642
      }
    },
    {
      "timestamp": "2026-06-12T12:47:09.316104-04:00",
      "strategy": "macd_crossover",
      "strategy_type": "daily",
      "vix_type": "TREND",
      "symbol": "IONQ",
      "signal": "hold",
      "price": 58.21,
      "atr": 5.9636,
      "qty": 0,
      "stop_price": null,
      "tp_price": null,
      "executed": false,
      "skip_reason": "no_signal",
      "order_id": null,
      "vix": 22.59,
      "vix_reason": "vix_reduced_to_50pct (22.6 >= 20)",
      "indicators": {
        "macd": 2.343,
        "macd_sig": 4.0907,
        "macd_hist": -1.7476
      }
    },
    {
      "timestamp": "2026-06-12T12:47:09.316104-04:00",
      "strategy": "macd_crossover",
      "strategy_type": "daily",
      "vix_type": "TREND",
      "symbol": "QCOM",
      "signal": "hold",
      "price": 213.3,
      "atr": 17.4967,
      "qty": 0,
      "stop_price": null,
      "tp_price": null,
      "executed": false,
      "skip_reason": "no_signal",
      "order_id": null,
      "vix": 22.59,
      "vix_reason": "vix_reduced_to_50pct (22.6 >= 20)",
      "indicators": {
        "macd": 5.6456,
        "macd_sig": 12.0643,
        "macd_hist": -6.4187
      }
    },
    {
      "timestamp": "2026-06-12T12:47:09.316104-04:00",
      "strategy": "macd_crossover",
      "strategy_type": "daily",
      "vix_type": "TREND",
      "symbol": "SMCI",
      "signal": "hold",
      "price": 30.71,
      "atr": 4.5214,
      "qty": 0,
      "stop_price": null,
      "tp_price": null,
      "executed": false,
      "skip_reason": "no_signal",
      "order_id": null,
      "vix": 22.59,
      "vix_reason": "vix_reduced_to_50pct (22.6 >= 20)",
      "indicators": {
        "macd": 0.8801,
        "macd_sig": 2.7082,
        "macd_hist": -1.8281
      }
    },
    {
      "timestamp": "2026-06-12T12:47:09.316104-04:00",
      "strategy": "macd_crossover",
      "strategy_type": "daily",
      "vix_type": "TREND",
      "symbol": "SMH",
      "signal": "hold",
      "price": 620.8,
      "atr": 31.6151,
      "qty": 0,
      "stop_price": null,
      "tp_price": null,
      "executed": false,
      "skip_reason": "no_signal",
      "order_id": null,
      "vix": 22.59,
      "vix_reason": "vix_reduced_to_50pct (22.6 >= 20)",
      "indicators": {
        "macd": 20.9904,
        "macd_sig": 25.0693,
        "macd_hist": -4.079
      }
    },
    {
      "timestamp": "2026-06-12T12:47:09.316104-04:00",
      "strategy": "macd_crossover",
      "strategy_type": "daily",
      "vix_type": "TREND",
      "symbol": "ORCL",
      "signal": "hold",
      "price": 182.54,
      "atr": 15.2026,
      "qty": 0,
      "stop_price": null,
      "tp_price": null,
      "executed": false,
      "skip_reason": "no_signal",
      "order_id": null,
      "vix": 22.59,
      "vix_reason": "vix_reduced_to_50pct (22.6 >= 20)",
      "indicators": {
        "macd": 3.8908,
        "macd_sig": 9.2165,
        "macd_hist": -5.3257
      }
    },
    {
      "timestamp": "2026-06-12T12:47:09.316104-04:00",
      "strategy": "macd_crossover",
      "strategy_type": "daily",
      "vix_type": "TREND",
      "symbol": "TXN",
      "signal": "hold",
      "price": 301.0,
      "atr": 12.9644,
      "qty": 0,
      "stop_price": null,
      "tp_price": null,
      "executed": false,
      "skip_reason": "no_signal",
      "order_id": null,
      "vix": 22.59,
      "vix_reason": "vix_reduced_to_50pct (22.6 >= 20)",
      "indicators": {
        "macd": 4.3536,
        "macd_sig": 8.0357,
        "macd_hist": -3.6821
      }
    },
    {
      "timestamp": "2026-06-12T12:47:09.316104-04:00",
      "strategy": "macd_crossover",
      "strategy_type": "daily",
      "vix_type": "TREND",
      "symbol": "XLY",
      "signal": "hold",
      "price": 115.64,
      "atr": 2.2368,
      "qty": 0,
      "stop_price": null,
      "tp_price": null,
      "executed": false,
      "skip_reason": "no_signal",
      "order_id": null,
      "vix": 22.59,
      "vix_reason": "vix_reduced_to_50pct (22.6 >= 20)",
      "indicators": {
        "macd": -0.6042,
        "macd_sig": -0.1558,
        "macd_hist": -0.4484
      }
    },
    {
      "timestamp": "2026-06-12T12:47:09.316104-04:00",
      "strategy": "macd_crossover",
      "strategy_type": "daily",
      "vix_type": "TREND",
      "symbol": "CVX",
      "signal": "hold",
      "price": 187.7,
      "atr": 4.294,
      "qty": 0,
      "stop_price": null,
      "tp_price": null,
      "executed": false,
      "skip_reason": "no_signal",
      "order_id": null,
      "vix": 22.59,
      "vix_reason": "vix_reduced_to_50pct (22.6 >= 20)",
      "indicators": {
        "macd": -0.3966,
        "macd_sig": -0.5355,
        "macd_hist": 0.1389
      }
    },
    {
      "timestamp": "2026-06-12T12:47:09.316104-04:00",
      "strategy": "macd_crossover",
      "strategy_type": "daily",
      "vix_type": "TREND",
      "symbol": "COP",
      "signal": "hold",
      "price": 117.89,
      "atr": 3.6947,
      "qty": 0,
      "stop_price": null,
      "tp_price": null,
      "executed": false,
      "skip_reason": "no_signal",
      "order_id": null,
      "vix": 22.59,
      "vix_reason": "vix_reduced_to_50pct (22.6 >= 20)",
      "indicators": {
        "macd": -0.8288,
        "macd_sig": -0.9614,
        "macd_hist": 0.1326
      }
    },
    {
      "timestamp": "2026-06-12T12:47:09.316104-04:00",
      "strategy": "macd_crossover",
      "strategy_type": "daily",
      "vix_type": "TREND",
      "symbol": "SCHW",
      "signal": "hold",
      "price": 91.05,
      "atr": 2.1074,
      "qty": 0,
      "stop_price": null,
      "tp_price": null,
      "executed": false,
      "skip_reason": "no_signal",
      "order_id": null,
      "vix": 22.59,
      "vix_reason": "vix_reduced_to_50pct (22.6 >= 20)",
      "indicators": {
        "macd": -0.4542,
        "macd_sig": -0.8535,
        "macd_hist": 0.3993
      }
    },
    {
      "timestamp": "2026-06-12T12:47:09.316104-04:00",
      "strategy": "macd_crossover",
      "strategy_type": "daily",
      "vix_type": "TREND",
      "symbol": "V",
      "signal": "hold",
      "price": 323.83,
      "atr": 6.8306,
      "qty": 0,
      "stop_price": null,
      "tp_price": null,
      "executed": false,
      "skip_reason": "no_signal",
      "order_id": null,
      "vix": 22.59,
      "vix_reason": "vix_reduced_to_50pct (22.6 >= 20)",
      "indicators": {
        "macd": 0.1843,
        "macd_sig": 0.7409,
        "macd_hist": -0.5566
      }
    },
    {
      "timestamp": "2026-06-12T12:47:09.316104-04:00",
      "strategy": "macd_crossover",
      "strategy_type": "daily",
      "vix_type": "TREND",
      "symbol": "BAC",
      "signal": "hold",
      "price": 55.66,
      "atr": 1.1121,
      "qty": 0,
      "stop_price": null,
      "tp_price": null,
      "executed": false,
      "skip_reason": "no_signal",
      "order_id": null,
      "vix": 22.59,
      "vix_reason": "vix_reduced_to_50pct (22.6 >= 20)",
      "indicators": {
        "macd": 0.9091,
        "macd_sig": 0.5141,
        "macd_hist": 0.395
      }
    },
    {
      "timestamp": "2026-06-12T12:47:09.316104-04:00",
      "strategy": "macd_crossover",
      "strategy_type": "daily",
      "vix_type": "TREND",
      "symbol": "XLV",
      "signal": "hold",
      "price": 153.86,
      "atr": 2.3209,
      "qty": 0,
      "stop_price": null,
      "tp_price": null,
      "executed": false,
      "skip_reason": "no_signal",
      "order_id": null,
      "vix": 22.59,
      "vix_reason": "vix_reduced_to_50pct (22.6 >= 20)",
      "indicators": {
        "macd": 1.8882,
        "macd_sig": 1.3685,
        "macd_hist": 0.5197
      }
    },
    {
      "timestamp": "2026-06-12T12:47:09.316104-04:00",
      "strategy": "macd_crossover",
      "strategy_type": "daily",
      "vix_type": "TREND",
      "symbol": "XOM",
      "signal": "hold",
      "price": 147.92,
      "atr": 3.8585,
      "qty": 0,
      "stop_price": null,
      "tp_price": null,
      "executed": false,
      "skip_reason": "no_signal",
      "order_id": null,
      "vix": 22.59,
      "vix_reason": "vix_reduced_to_50pct (22.6 >= 20)",
      "indicators": {
        "macd": -1.0941,
        "macd_sig": -0.7908,
        "macd_hist": -0.3032
      }
    },
    {
      "timestamp": "2026-06-12T12:47:09.316104-04:00",
      "strategy": "triple_ema",
      "strategy_type": "daily",
      "vix_type": "TREND",
      "symbol": "SPY",
      "signal": "hold",
      "price": 740.94,
      "atr": 10.9482,
      "qty": 0,
      "stop_price": null,
      "tp_price": null,
      "executed": false,
      "skip_reason": "no_signal",
      "order_id": null,
      "vix": 22.59,
      "vix_reason": "vix_reduced_to_50pct (22.6 >= 20)",
      "indicators": {
        "ema_fast": 740.44,
        "ema_mid": 740.34,
        "ema_slow": 723.27
      }
    },
    {
      "timestamp": "2026-06-12T12:47:09.316104-04:00",
      "strategy": "triple_ema",
      "strategy_type": "daily",
      "vix_type": "TREND",
      "symbol": "QQQ",
      "signal": "hold",
      "price": 720.66,
      "atr": 17.4929,
      "qty": 0,
      "stop_price": null,
      "tp_price": null,
      "executed": false,
      "skip_reason": "no_signal",
      "order_id": null,
      "vix": 22.59,
      "vix_reason": "vix_reduced_to_50pct (22.6 >= 20)",
      "indicators": {
        "ema_fast": 717.19,
        "ema_mid": 714.39,
        "ema_slow": 684.26
      }
    },
    {
      "timestamp": "2026-06-12T12:47:09.316104-04:00",
      "strategy": "triple_ema",
      "strategy_type": "daily",
      "vix_type": "TREND",
      "symbol": "IWM",
      "signal": "hold",
      "price": 293.86,
      "atr": 6.7917,
      "qty": 0,
      "stop_price": null,
      "tp_price": null,
      "executed": false,
      "skip_reason": "no_signal",
      "order_id": null,
      "vix": 22.59,
      "vix_reason": "vix_reduced_to_50pct (22.6 >= 20)",
      "indicators": {
        "ema_fast": 288.13,
        "ema_mid": 285.69,
        "ema_slow": 277.68
      }
    },
    {
      "timestamp": "2026-06-12T12:47:09.316104-04:00",
      "strategy": "triple_ema",
      "strategy_type": "daily",
      "vix_type": "TREND",
      "symbol": "GLD",
      "signal": "hold",
      "price": 386.68,
      "atr": 9.1899,
      "qty": 0,
      "stop_price": null,
      "tp_price": null,
      "executed": false,
      "skip_reason": "no_signal",
      "order_id": null,
      "vix": 22.59,
      "vix_reason": "vix_reduced_to_50pct (22.6 >= 20)",
      "indicators": {
        "ema_fast": 392.56,
        "ema_mid": 404.51,
        "ema_slow": 418.21
      }
    },
    {
      "timestamp": "2026-06-12T12:47:09.316104-04:00",
      "strategy": "triple_ema",
      "strategy_type": "daily",
      "vix_type": "TREND",
      "symbol": "XLK",
      "signal": "hold",
      "price": 184.93,
      "atr": 6.4307,
      "qty": 0,
      "stop_price": null,
      "tp_price": null,
      "executed": false,
      "skip_reason": "no_signal",
      "order_id": null,
      "vix": 22.59,
      "vix_reason": "vix_reduced_to_50pct (22.6 >= 20)",
      "indicators": {
        "ema_fast": 184.08,
        "ema_mid": 181.84,
        "ema_slow": 170.89
      }
    },
    {
      "timestamp": "2026-06-12T12:47:09.316104-04:00",
      "strategy": "triple_ema",
      "strategy_type": "daily",
      "vix_type": "TREND",
      "symbol": "XLE",
      "signal": "hold",
      "price": 57.86,
      "atr": 1.419,
      "qty": 0,
      "stop_price": null,
      "tp_price": null,
      "executed": false,
      "skip_reason": "no_signal",
      "order_id": null,
      "vix": 22.59,
      "vix_reason": "vix_reduced_to_50pct (22.6 >= 20)",
      "indicators": {
        "ema_fast": 57.82,
        "ema_mid": 57.96,
        "ema_slow": 57.88
      }
    },
    {
      "timestamp": "2026-06-12T12:47:09.316104-04:00",
      "strategy": "triple_ema",
      "strategy_type": "daily",
      "vix_type": "TREND",
      "symbol": "XLF",
      "signal": "hold",
      "price": 53.25,
      "atr": 0.7084,
      "qty": 0,
      "stop_price": null,
      "tp_price": null,
      "executed": false,
      "skip_reason": "no_signal",
      "order_id": null,
      "vix": 22.59,
      "vix_reason": "vix_reduced_to_50pct (22.6 >= 20)",
      "indicators": {
        "ema_fast": 52.38,
        "ema_mid": 51.95,
        "ema_slow": 51.66
      }
    },
    {
      "timestamp": "2026-06-12T12:47:09.316104-04:00",
      "strategy": "triple_ema",
      "strategy_type": "daily",
      "vix_type": "TREND",
      "symbol": "ARM",
      "signal": "hold",
      "price": 370.89,
      "atr": 37.9369,
      "qty": 0,
      "stop_price": null,
      "tp_price": null,
      "executed": false,
      "skip_reason": "no_signal",
      "order_id": null,
      "vix": 22.59,
      "vix_reason": "vix_reduced_to_50pct (22.6 >= 20)",
      "indicators": {
        "ema_fast": 348.0,
        "ema_mid": 320.39,
        "ema_slow": 255.47
      }
    },
    {
      "timestamp": "2026-06-12T12:47:09.316104-04:00",
      "strategy": "triple_ema",
      "strategy_type": "daily",
      "vix_type": "TREND",
      "symbol": "MRVL",
      "signal": "hold",
      "price": 284.12,
      "atr": 31.2639,
      "qty": 0,
      "stop_price": null,
      "tp_price": null,
      "executed": false,
      "skip_reason": "no_signal",
      "order_id": null,
      "vix": 22.59,
      "vix_reason": "vix_reduced_to_50pct (22.6 >= 20)",
      "indicators": {
        "ema_fast": 270.45,
        "ema_mid": 239.82,
        "ema_slow": 189.13
      }
    },
    {
      "timestamp": "2026-06-12T12:47:09.316104-04:00",
      "strategy": "triple_ema",
      "strategy_type": "daily",
      "vix_type": "TREND",
      "symbol": "MU",
      "signal": "hold",
      "price": 995.54,
      "atr": 82.5544,
      "qty": 0,
      "stop_price": null,
      "tp_price": null,
      "executed": false,
      "skip_reason": "no_signal",
      "order_id": null,
      "vix": 22.59,
      "vix_reason": "vix_reduced_to_50pct (22.6 >= 20)",
      "indicators": {
        "ema_fast": 959.02,
        "ema_mid": 887.77,
        "ema_slow": 716.83
      }
    },
    {
      "timestamp": "2026-06-12T12:47:09.316104-04:00",
      "strategy": "triple_ema",
      "strategy_type": "daily",
      "vix_type": "TREND",
      "symbol": "AMD",
      "signal": "hold",
      "price": 511.15,
      "atr": 35.1847,
      "qty": 0,
      "stop_price": null,
      "tp_price": null,
      "executed": false,
      "skip_reason": "no_signal",
      "order_id": null,
      "vix": 22.59,
      "vix_reason": "vix_reduced_to_50pct (22.6 >= 20)",
      "indicators": {
        "ema_fast": 490.95,
        "ema_mid": 471.77,
        "ema_slow": 396.13
      }
    },
    {
      "timestamp": "2026-06-12T12:47:09.316104-04:00",
      "strategy": "triple_ema",
      "strategy_type": "daily",
      "vix_type": "TREND",
      "symbol": "DDOG",
      "signal": "hold",
      "price": 231.7,
      "atr": 13.1927,
      "qty": 0,
      "stop_price": null,
      "tp_price": null,
      "executed": false,
      "skip_reason": "no_signal",
      "order_id": null,
      "vix": 22.59,
      "vix_reason": "vix_reduced_to_50pct (22.6 >= 20)",
      "indicators": {
        "ema_fast": 234.14,
        "ema_mid": 223.79,
        "ema_slow": 188.9
      }
    },
    {
      "timestamp": "2026-06-12T12:47:09.316104-04:00",
      "strategy": "triple_ema",
      "strategy_type": "daily",
      "vix_type": "TREND",
      "symbol": "INTC",
      "signal": "hold",
      "price": 124.61,
      "atr": 10.0315,
      "qty": 0,
      "stop_price": null,
      "tp_price": null,
      "executed": false,
      "skip_reason": "no_signal",
      "order_id": null,
      "vix": 22.59,
      "vix_reason": "vix_reduced_to_50pct (22.6 >= 20)",
      "indicators": {
        "ema_fast": 113.92,
        "ema_mid": 111.07,
        "ema_slow": 95.11
      }
    },
    {
      "timestamp": "2026-06-12T12:47:09.316104-04:00",
      "strategy": "triple_ema",
      "strategy_type": "daily",
      "vix_type": "TREND",
      "symbol": "PANW",
      "signal": "hold",
      "price": 279.78,
      "atr": 13.6913,
      "qty": 0,
      "stop_price": null,
      "tp_price": null,
      "executed": false,
      "skip_reason": "no_signal",
      "order_id": null,
      "vix": 22.59,
      "vix_reason": "vix_reduced_to_50pct (22.6 >= 20)",
      "indicators": {
        "ema_fast": 273.02,
        "ema_mid": 259.17,
        "ema_slow": 225.51
      }
    },
    {
      "timestamp": "2026-06-12T12:47:09.316104-04:00",
      "strategy": "triple_ema",
      "strategy_type": "daily",
      "vix_type": "TREND",
      "symbol": "RKLB",
      "signal": "hold",
      "price": 106.98,
      "atr": 12.155,
      "qty": 0,
      "stop_price": null,
      "tp_price": null,
      "executed": false,
      "skip_reason": "no_signal",
      "order_id": null,
      "vix": 22.59,
      "vix_reason": "vix_reduced_to_50pct (22.6 >= 20)",
      "indicators": {
        "ema_fast": 113.27,
        "ema_mid": 116.07,
        "ema_slow": 103.54
      }
    },
    {
      "timestamp": "2026-06-12T12:47:09.316104-04:00",
      "strategy": "triple_ema",
      "strategy_type": "daily",
      "vix_type": "TREND",
      "symbol": "SNOW",
      "signal": "hold",
      "price": 237.04,
      "atr": 14.4445,
      "qty": 0,
      "stop_price": null,
      "tp_price": null,
      "executed": false,
      "skip_reason": "no_signal",
      "order_id": null,
      "vix": 22.59,
      "vix_reason": "vix_reduced_to_50pct (22.6 >= 20)",
      "indicators": {
        "ema_fast": 237.78,
        "ema_mid": 217.23,
        "ema_slow": 190.39
      }
    },
    {
      "timestamp": "2026-06-12T12:47:09.316104-04:00",
      "strategy": "triple_ema",
      "strategy_type": "daily",
      "vix_type": "TREND",
      "symbol": "IONQ",
      "signal": "hold",
      "price": 58.21,
      "atr": 5.9636,
      "qty": 0,
      "stop_price": null,
      "tp_price": null,
      "executed": false,
      "skip_reason": "no_signal",
      "order_id": null,
      "vix": 22.59,
      "vix_reason": "vix_reduced_to_50pct (22.6 >= 20)",
      "indicators": {
        "ema_fast": 59.93,
        "ema_mid": 59.27,
        "ema_slow": 52.15
      }
    },
    {
      "timestamp": "2026-06-12T12:47:09.316104-04:00",
      "strategy": "triple_ema",
      "strategy_type": "daily",
      "vix_type": "TREND",
      "symbol": "QCOM",
      "signal": "hold",
      "price": 213.3,
      "atr": 17.4967,
      "qty": 0,
      "stop_price": null,
      "tp_price": null,
      "executed": false,
      "skip_reason": "no_signal",
      "order_id": null,
      "vix": 22.59,
      "vix_reason": "vix_reduced_to_50pct (22.6 >= 20)",
      "indicators": {
        "ema_fast": 213.83,
        "ema_mid": 214.28,
        "ema_slow": 191.67
      }
    },
    {
      "timestamp": "2026-06-12T12:47:09.316104-04:00",
      "strategy": "triple_ema",
      "strategy_type": "daily",
      "vix_type": "TREND",
      "symbol": "SMCI",
      "signal": "hold",
      "price": 30.71,
      "atr": 4.5214,
      "qty": 0,
      "stop_price": null,
      "tp_price": null,
      "executed": false,
      "skip_reason": "no_signal",
      "order_id": null,
      "vix": 22.59,
      "vix_reason": "vix_reduced_to_50pct (22.6 >= 20)",
      "indicators": {
        "ema_fast": 36.55,
        "ema_mid": 37.3,
        "ema_slow": 34.07
      }
    },
    {
      "timestamp": "2026-06-12T12:47:09.316104-04:00",
      "strategy": "triple_ema",
      "strategy_type": "daily",
      "vix_type": "TREND",
      "symbol": "SMH",
      "signal": "hold",
      "price": 620.8,
      "atr": 31.6151,
      "qty": 0,
      "stop_price": null,
      "tp_price": null,
      "executed": false,
      "skip_reason": "no_signal",
      "order_id": null,
      "vix": 22.59,
      "vix_reason": "vix_reduced_to_50pct (22.6 >= 20)",
      "indicators": {
        "ema_fast": 601.99,
        "ema_mid": 586.14,
        "ema_slow": 532.02
      }
    },
    {
      "timestamp": "2026-06-12T12:47:09.316104-04:00",
      "strategy": "triple_ema",
      "strategy_type": "daily",
      "vix_type": "TREND",
      "symbol": "ORCL",
      "signal": "hold",
      "price": 182.54,
      "atr": 15.2026,
      "qty": 0,
      "stop_price": null,
      "tp_price": null,
      "executed": false,
      "skip_reason": "no_signal",
      "order_id": null,
      "vix": 22.59,
      "vix_reason": "vix_reduced_to_50pct (22.6 >= 20)",
      "indicators": {
        "ema_fast": 201.48,
        "ema_mid": 202.49,
        "ema_slow": 189.23
      }
    },
    {
      "timestamp": "2026-06-12T12:47:09.316104-04:00",
      "strategy": "triple_ema",
      "strategy_type": "daily",
      "vix_type": "TREND",
      "symbol": "TXN",
      "signal": "buy",
      "price": 301.0,
      "atr": 12.9644,
      "qty": 0,
      "stop_price": null,
      "tp_price": null,
      "executed": false,
      "skip_reason": "ma20_bear_block (SPY 740.94 < MA20 745.00)",
      "order_id": null,
      "vix": 22.59,
      "vix_reason": "vix_reduced_to_50pct (22.6 >= 20)",
      "indicators": {
        "ema_fast": 295.87,
        "ema_mid": 295.33,
        "ema_slow": 272.33
      }
    },
    {
      "timestamp": "2026-06-12T12:47:09.316104-04:00",
      "strategy": "triple_ema",
      "strategy_type": "daily",
      "vix_type": "TREND",
      "symbol": "XLY",
      "signal": "hold",
      "price": 115.64,
      "atr": 2.2368,
      "qty": 0,
      "stop_price": null,
      "tp_price": null,
      "executed": false,
      "skip_reason": "no_signal",
      "order_id": null,
      "vix": 22.59,
      "vix_reason": "vix_reduced_to_50pct (22.6 >= 20)",
      "indicators": {
        "ema_fast": 116.02,
        "ema_mid": 117.01,
        "ema_slow": 117.89
      }
    },
    {
      "timestamp": "2026-06-12T12:47:09.316104-04:00",
      "strategy": "triple_ema",
      "strategy_type": "daily",
      "vix_type": "TREND",
      "symbol": "CVX",
      "signal": "hold",
      "price": 187.7,
      "atr": 4.294,
      "qty": 0,
      "stop_price": null,
      "tp_price": null,
      "executed": false,
      "skip_reason": "no_signal",
      "order_id": null,
      "vix": 22.59,
      "vix_reason": "vix_reduced_to_50pct (22.6 >= 20)",
      "indicators": {
        "ema_fast": 187.58,
        "ema_mid": 187.82,
        "ema_slow": 187.95
      }
    },
    {
      "timestamp": "2026-06-12T12:47:09.316104-04:00",
      "strategy": "triple_ema",
      "strategy_type": "daily",
      "vix_type": "TREND",
      "symbol": "COP",
      "signal": "hold",
      "price": 117.89,
      "atr": 3.6947,
      "qty": 0,
      "stop_price": null,
      "tp_price": null,
      "executed": false,
      "skip_reason": "no_signal",
      "order_id": null,
      "vix": 22.59,
      "vix_reason": "vix_reduced_to_50pct (22.6 >= 20)",
      "indicators": {
        "ema_fast": 117.63,
        "ema_mid": 118.3,
        "ema_slow": 118.72
      }
    },
    {
      "timestamp": "2026-06-12T12:47:09.316104-04:00",
      "strategy": "triple_ema",
      "strategy_type": "daily",
      "vix_type": "TREND",
      "symbol": "SCHW",
      "signal": "hold",
      "price": 91.05,
      "atr": 2.1074,
      "qty": 0,
      "stop_price": null,
      "tp_price": null,
      "executed": false,
      "skip_reason": "no_signal",
      "order_id": null,
      "vix": 22.59,
      "vix_reason": "vix_reduced_to_50pct (22.6 >= 20)",
      "indicators": {
        "ema_fast": 89.07,
        "ema_mid": 89.14,
        "ema_slow": 90.93
      }
    },
    {
      "timestamp": "2026-06-12T12:47:09.316104-04:00",
      "strategy": "triple_ema",
      "strategy_type": "daily",
      "vix_type": "TREND",
      "symbol": "V",
      "signal": "hold",
      "price": 323.83,
      "atr": 6.8306,
      "qty": 0,
      "stop_price": null,
      "tp_price": null,
      "executed": false,
      "skip_reason": "no_signal",
      "order_id": null,
      "vix": 22.59,
      "vix_reason": "vix_reduced_to_50pct (22.6 >= 20)",
      "indicators": {
        "ema_fast": 322.15,
        "ema_mid": 322.53,
        "ema_slow": 320.64
      }
    },
    {
      "timestamp": "2026-06-12T12:47:09.316104-04:00",
      "strategy": "triple_ema",
      "strategy_type": "daily",
      "vix_type": "TREND",
      "symbol": "BAC",
      "signal": "hold",
      "price": 55.66,
      "atr": 1.1121,
      "qty": 0,
      "stop_price": null,
      "tp_price": null,
      "executed": false,
      "skip_reason": "no_signal",
      "order_id": null,
      "vix": 22.59,
      "vix_reason": "vix_reduced_to_50pct (22.6 >= 20)",
      "indicators": {
        "ema_fast": 54.25,
        "ema_mid": 53.05,
        "ema_slow": 52.19
      }
    },
    {
      "timestamp": "2026-06-12T12:47:09.316104-04:00",
      "strategy": "triple_ema",
      "strategy_type": "daily",
      "vix_type": "TREND",
      "symbol": "XLV",
      "signal": "hold",
      "price": 153.86,
      "atr": 2.3209,
      "qty": 0,
      "stop_price": null,
      "tp_price": null,
      "executed": false,
      "skip_reason": "no_signal",
      "order_id": null,
      "vix": 22.59,
      "vix_reason": "vix_reduced_to_50pct (22.6 >= 20)",
      "indicators": {
        "ema_fast": 152.56,
        "ema_mid": 150.29,
        "ema_slow": 149.07
      }
    },
    {
      "timestamp": "2026-06-12T12:47:09.316104-04:00",
      "strategy": "triple_ema",
      "strategy_type": "daily",
      "vix_type": "TREND",
      "symbol": "XOM",
      "signal": "hold",
      "price": 147.92,
      "atr": 3.8585,
      "qty": 0,
      "stop_price": null,
      "tp_price": null,
      "executed": false,
      "skip_reason": "no_signal",
      "order_id": null,
      "vix": 22.59,
      "vix_reason": "vix_reduced_to_50pct (22.6 >= 20)",
      "indicators": {
        "ema_fast": 149.27,
        "ema_mid": 150.57,
        "ema_slow": 151.03
      }
    },
    {
      "timestamp": "2026-06-12T12:47:09.316104-04:00",
      "strategy": "ema_crossover",
      "strategy_type": "daily",
      "vix_type": "TREND",
      "symbol": "SPY",
      "signal": "hold",
      "price": 740.94,
      "atr": 10.9482,
      "qty": 0,
      "stop_price": null,
      "tp_price": null,
      "executed": false,
      "skip_reason": "no_signal",
      "order_id": null,
      "vix": 22.59,
      "vix_reason": "vix_reduced_to_50pct (22.6 >= 20)",
      "indicators": {
        "ema_fast": 741.8,
        "ema_slow": 738.08,
        "diff": 3.7186
      }
    },
    {
      "timestamp": "2026-06-12T12:47:09.316104-04:00",
      "strategy": "ema_crossover",
      "strategy_type": "daily",
      "vix_type": "TREND",
      "symbol": "QQQ",
      "signal": "hold",
      "price": 720.66,
      "atr": 17.4929,
      "qty": 0,
      "stop_price": null,
      "tp_price": null,
      "executed": false,
      "skip_reason": "no_signal",
      "order_id": null,
      "vix": 22.59,
      "vix_reason": "vix_reduced_to_50pct (22.6 >= 20)",
      "indicators": {
        "ema_fast": 718.36,
        "ema_slow": 710.11,
        "diff": 8.2503
      }
    },
    {
      "timestamp": "2026-06-12T12:47:09.316104-04:00",
      "strategy": "ema_crossover",
      "strategy_type": "daily",
      "vix_type": "TREND",
      "symbol": "IWM",
      "signal": "hold",
      "price": 293.86,
      "atr": 6.7917,
      "qty": 0,
      "stop_price": null,
      "tp_price": null,
      "executed": false,
      "skip_reason": "no_signal",
      "order_id": null,
      "vix": 22.59,
      "vix_reason": "vix_reduced_to_50pct (22.6 >= 20)",
      "indicators": {
        "ema_fast": 287.47,
        "ema_slow": 284.49,
        "diff": 2.9764
      }
    },
    {
      "timestamp": "2026-06-12T12:47:09.316104-04:00",
      "strategy": "ema_crossover",
      "strategy_type": "daily",
      "vix_type": "TREND",
      "symbol": "GLD",
      "signal": "hold",
      "price": 386.68,
      "atr": 9.1899,
      "qty": 0,
      "stop_price": null,
      "tp_price": null,
      "executed": false,
      "skip_reason": "no_signal",
      "order_id": null,
      "vix": 22.59,
      "vix_reason": "vix_reduced_to_50pct (22.6 >= 20)",
      "indicators": {
        "ema_fast": 397.15,
        "ema_slow": 407.55,
        "diff": -10.4048
      }
    },
    {
      "timestamp": "2026-06-12T12:47:09.316104-04:00",
      "strategy": "ema_crossover",
      "strategy_type": "daily",
      "vix_type": "TREND",
      "symbol": "XLK",
      "signal": "hold",
      "price": 184.93,
      "atr": 6.4307,
      "qty": 0,
      "stop_price": null,
      "tp_price": null,
      "executed": false,
      "skip_reason": "no_signal",
      "order_id": null,
      "vix": 22.59,
      "vix_reason": "vix_reduced_to_50pct (22.6 >= 20)",
      "indicators": {
        "ema_fast": 184.17,
        "ema_slow": 179.93,
        "diff": 4.236
      }
    },
    {
      "timestamp": "2026-06-12T12:47:09.316104-04:00",
      "strategy": "ema_crossover",
      "strategy_type": "daily",
      "vix_type": "TREND",
      "symbol": "XLE",
      "signal": "hold",
      "price": 57.86,
      "atr": 1.419,
      "qty": 0,
      "stop_price": null,
      "tp_price": null,
      "executed": false,
      "skip_reason": "no_signal",
      "order_id": null,
      "vix": 22.59,
      "vix_reason": "vix_reduced_to_50pct (22.6 >= 20)",
      "indicators": {
        "ema_fast": 57.89,
        "ema_slow": 57.97,
        "diff": -0.0839
      }
    },
    {
      "timestamp": "2026-06-12T12:47:09.316104-04:00",
      "strategy": "ema_crossover",
      "strategy_type": "daily",
      "vix_type": "TREND",
      "symbol": "XLF",
      "signal": "hold",
      "price": 53.25,
      "atr": 0.7084,
      "qty": 0,
      "stop_price": null,
      "tp_price": null,
      "executed": false,
      "skip_reason": "no_signal",
      "order_id": null,
      "vix": 22.59,
      "vix_reason": "vix_reduced_to_50pct (22.6 >= 20)",
      "indicators": {
        "ema_fast": 52.19,
        "ema_slow": 51.87,
        "diff": 0.3217
      }
    },
    {
      "timestamp": "2026-06-12T12:47:09.316104-04:00",
      "strategy": "ema_crossover",
      "strategy_type": "daily",
      "vix_type": "TREND",
      "symbol": "ARM",
      "signal": "hold",
      "price": 370.89,
      "atr": 37.9369,
      "qty": 0,
      "stop_price": null,
      "tp_price": null,
      "executed": false,
      "skip_reason": "no_signal",
      "order_id": null,
      "vix": 22.59,
      "vix_reason": "vix_reduced_to_50pct (22.6 >= 20)",
      "indicators": {
        "ema_fast": 342.03,
        "ema_slow": 308.19,
        "diff": 33.8402
      }
    },
    {
      "timestamp": "2026-06-12T12:47:09.316104-04:00",
      "strategy": "ema_crossover",
      "strategy_type": "daily",
      "vix_type": "TREND",
      "symbol": "MRVL",
      "signal": "hold",
      "price": 284.12,
      "atr": 31.2639,
      "qty": 0,
      "stop_price": null,
      "tp_price": null,
      "executed": false,
      "skip_reason": "no_signal",
      "order_id": null,
      "vix": 22.59,
      "vix_reason": "vix_reduced_to_50pct (22.6 >= 20)",
      "indicators": {
        "ema_fast": 260.83,
        "ema_slow": 229.84,
        "diff": 30.9919
      }
    },
    {
      "timestamp": "2026-06-12T12:47:09.316104-04:00",
      "strategy": "ema_crossover",
      "strategy_type": "daily",
      "vix_type": "TREND",
      "symbol": "MU",
      "signal": "hold",
      "price": 995.54,
      "atr": 82.5544,
      "qty": 0,
      "stop_price": null,
      "tp_price": null,
      "executed": false,
      "skip_reason": "no_signal",
      "order_id": null,
      "vix": 22.59,
      "vix_reason": "vix_reduced_to_50pct (22.6 >= 20)",
      "indicators": {
        "ema_fast": 941.92,
        "ema_slow": 856.64,
        "diff": 85.273
      }
    },
    {
      "timestamp": "2026-06-12T12:47:09.316104-04:00",
      "strategy": "ema_crossover",
      "strategy_type": "daily",
      "vix_type": "TREND",
      "symbol": "AMD",
      "signal": "hold",
      "price": 511.15,
      "atr": 35.1847,
      "qty": 0,
      "stop_price": null,
      "tp_price": null,
      "executed": false,
      "skip_reason": "no_signal",
      "order_id": null,
      "vix": 22.59,
      "vix_reason": "vix_reduced_to_50pct (22.6 >= 20)",
      "indicators": {
        "ema_fast": 488.25,
        "ema_slow": 459.79,
        "diff": 28.4617
      }
    },
    {
      "timestamp": "2026-06-12T12:47:09.316104-04:00",
      "strategy": "ema_crossover",
      "strategy_type": "daily",
      "vix_type": "TREND",
      "symbol": "DDOG",
      "signal": "hold",
      "price": 231.7,
      "atr": 13.1927,
      "qty": 0,
      "stop_price": null,
      "tp_price": null,
      "executed": false,
      "skip_reason": "no_signal",
      "order_id": null,
      "vix": 22.59,
      "vix_reason": "vix_reduced_to_50pct (22.6 >= 20)",
      "indicators": {
        "ema_fast": 233.02,
        "ema_slow": 217.52,
        "diff": 15.5007
      }
    },
    {
      "timestamp": "2026-06-12T12:47:09.316104-04:00",
      "strategy": "ema_crossover",
      "strategy_type": "daily",
      "vix_type": "TREND",
      "symbol": "INTC",
      "signal": "hold",
      "price": 124.61,
      "atr": 10.0315,
      "qty": 0,
      "stop_price": null,
      "tp_price": null,
      "executed": false,
      "skip_reason": "no_signal",
      "order_id": null,
      "vix": 22.59,
      "vix_reason": "vix_reduced_to_50pct (22.6 >= 20)",
      "indicators": {
        "ema_fast": 113.24,
        "ema_slow": 109.03,
        "diff": 4.2092
      }
    },
    {
      "timestamp": "2026-06-12T12:47:09.316104-04:00",
      "strategy": "ema_crossover",
      "strategy_type": "daily",
      "vix_type": "TREND",
      "symbol": "PANW",
      "signal": "hold",
      "price": 279.78,
      "atr": 13.6913,
      "qty": 0,
      "stop_price": null,
      "tp_price": null,
      "executed": false,
      "skip_reason": "no_signal",
      "order_id": null,
      "vix": 22.59,
      "vix_reason": "vix_reduced_to_50pct (22.6 >= 20)",
      "indicators": {
        "ema_fast": 270.0,
        "ema_slow": 252.75,
        "diff": 17.2494
      }
    },
    {
      "timestamp": "2026-06-12T12:47:09.316104-04:00",
      "strategy": "ema_crossover",
      "strategy_type": "daily",
      "vix_type": "TREND",
      "symbol": "RKLB",
      "signal": "hold",
      "price": 106.98,
      "atr": 12.155,
      "qty": 0,
      "stop_price": null,
      "tp_price": null,
      "executed": false,
      "skip_reason": "no_signal",
      "order_id": null,
      "vix": 22.59,
      "vix_reason": "vix_reduced_to_50pct (22.6 >= 20)",
      "indicators": {
        "ema_fast": 115.81,
        "ema_slow": 114.55,
        "diff": 1.2621
      }
    },
    {
      "timestamp": "2026-06-12T12:47:09.316104-04:00",
      "strategy": "ema_crossover",
      "strategy_type": "daily",
      "vix_type": "TREND",
      "symbol": "SNOW",
      "signal": "hold",
      "price": 237.04,
      "atr": 14.4445,
      "qty": 0,
      "stop_price": null,
      "tp_price": null,
      "executed": false,
      "skip_reason": "no_signal",
      "order_id": null,
      "vix": 22.59,
      "vix_reason": "vix_reduced_to_50pct (22.6 >= 20)",
      "indicators": {
        "ema_fast": 232.22,
        "ema_slow": 210.29,
        "diff": 21.9276
      }
    },
    {
      "timestamp": "2026-06-12T12:47:09.316104-04:00",
      "strategy": "ema_crossover",
      "strategy_type": "daily",
      "vix_type": "TREND",
      "symbol": "IONQ",
      "signal": "hold",
      "price": 58.21,
      "atr": 5.9636,
      "qty": 0,
      "stop_price": null,
      "tp_price": null,
      "executed": false,
      "skip_reason": "no_signal",
      "order_id": null,
      "vix": 22.59,
      "vix_reason": "vix_reduced_to_50pct (22.6 >= 20)",
      "indicators": {
        "ema_fast": 60.45,
        "ema_slow": 58.11,
        "diff": 2.343
      }
    },
    {
      "timestamp": "2026-06-12T12:47:09.316104-04:00",
      "strategy": "ema_crossover",
      "strategy_type": "daily",
      "vix_type": "TREND",
      "symbol": "QCOM",
      "signal": "hold",
      "price": 213.3,
      "atr": 17.4967,
      "qty": 0,
      "stop_price": null,
      "tp_price": null,
      "executed": false,
      "skip_reason": "no_signal",
      "order_id": null,
      "vix": 22.59,
      "vix_reason": "vix_reduced_to_50pct (22.6 >= 20)",
      "indicators": {
        "ema_fast": 216.53,
        "ema_slow": 210.88,
        "diff": 5.6456
      }
    },
    {
      "timestamp": "2026-06-12T12:47:09.316104-04:00",
      "strategy": "ema_crossover",
      "strategy_type": "daily",
      "vix_type": "TREND",
      "symbol": "SMCI",
      "signal": "hold",
      "price": 30.71,
      "atr": 4.5214,
      "qty": 0,
      "stop_price": null,
      "tp_price": null,
      "executed": false,
      "skip_reason": "no_signal",
      "order_id": null,
      "vix": 22.59,
      "vix_reason": "vix_reduced_to_50pct (22.6 >= 20)",
      "indicators": {
        "ema_fast": 37.6,
        "ema_slow": 36.72,
        "diff": 0.8801
      }
    },
    {
      "timestamp": "2026-06-12T12:47:09.316104-04:00",
      "strategy": "ema_crossover",
      "strategy_type": "daily",
      "vix_type": "TREND",
      "symbol": "SMH",
      "signal": "hold",
      "price": 620.8,
      "atr": 31.6151,
      "qty": 0,
      "stop_price": null,
      "tp_price": null,
      "executed": false,
      "skip_reason": "no_signal",
      "order_id": null,
      "vix": 22.59,
      "vix_reason": "vix_reduced_to_50pct (22.6 >= 20)",
      "indicators": {
        "ema_fast": 598.66,
        "ema_slow": 577.67,
        "diff": 20.9904
      }
    },
    {
      "timestamp": "2026-06-12T12:47:09.316104-04:00",
      "strategy": "ema_crossover",
      "strategy_type": "daily",
      "vix_type": "TREND",
      "symbol": "ORCL",
      "signal": "hold",
      "price": 182.54,
      "atr": 15.2026,
      "qty": 0,
      "stop_price": null,
      "tp_price": null,
      "executed": false,
      "skip_reason": "no_signal",
      "order_id": null,
      "vix": 22.59,
      "vix_reason": "vix_reduced_to_50pct (22.6 >= 20)",
      "indicators": {
        "ema_fast": 204.14,
        "ema_slow": 200.25,
        "diff": 3.8908
      }
    },
    {
      "timestamp": "2026-06-12T12:47:09.316104-04:00",
      "strategy": "ema_crossover",
      "strategy_type": "daily",
      "vix_type": "TREND",
      "symbol": "TXN",
      "signal": "hold",
      "price": 301.0,
      "atr": 12.9644,
      "qty": 0,
      "stop_price": null,
      "tp_price": null,
      "executed": false,
      "skip_reason": "no_signal",
      "order_id": null,
      "vix": 22.59,
      "vix_reason": "vix_reduced_to_50pct (22.6 >= 20)",
      "indicators": {
        "ema_fast": 296.95,
        "ema_slow": 292.6,
        "diff": 4.3536
      }
    },
    {
      "timestamp": "2026-06-12T12:47:09.316104-04:00",
      "strategy": "ema_crossover",
      "strategy_type": "daily",
      "vix_type": "TREND",
      "symbol": "XLY",
      "signal": "hold",
      "price": 115.64,
      "atr": 2.2368,
      "qty": 0,
      "stop_price": null,
      "tp_price": null,
      "executed": false,
      "skip_reason": "no_signal",
      "order_id": null,
      "vix": 22.59,
      "vix_reason": "vix_reduced_to_50pct (22.6 >= 20)",
      "indicators": {
        "ema_fast": 116.48,
        "ema_slow": 117.08,
        "diff": -0.6042
      }
    },
    {
      "timestamp": "2026-06-12T12:47:09.316104-04:00",
      "strategy": "ema_crossover",
      "strategy_type": "daily",
      "vix_type": "TREND",
      "symbol": "CVX",
      "signal": "hold",
      "price": 187.7,
      "atr": 4.294,
      "qty": 0,
      "stop_price": null,
      "tp_price": null,
      "executed": false,
      "skip_reason": "no_signal",
      "order_id": null,
      "vix": 22.59,
      "vix_reason": "vix_reduced_to_50pct (22.6 >= 20)",
      "indicators": {
        "ema_fast": 187.61,
        "ema_slow": 188.0,
        "diff": -0.3966
      }
    },
    {
      "timestamp": "2026-06-12T12:47:09.316104-04:00",
      "strategy": "ema_crossover",
      "strategy_type": "daily",
      "vix_type": "TREND",
      "symbol": "COP",
      "signal": "hold",
      "price": 117.89,
      "atr": 3.6947,
      "qty": 0,
      "stop_price": null,
      "tp_price": null,
      "executed": false,
      "skip_reason": "no_signal",
      "order_id": null,
      "vix": 22.59,
      "vix_reason": "vix_reduced_to_50pct (22.6 >= 20)",
      "indicators": {
        "ema_fast": 117.77,
        "ema_slow": 118.6,
        "diff": -0.8288
      }
    },
    {
      "timestamp": "2026-06-12T12:47:09.316104-04:00",
      "strategy": "ema_crossover",
      "strategy_type": "daily",
      "vix_type": "TREND",
      "symbol": "SCHW",
      "signal": "hold",
      "price": 91.05,
      "atr": 2.1074,
      "qty": 0,
      "stop_price": null,
      "tp_price": null,
      "executed": false,
      "skip_reason": "no_signal",
      "order_id": null,
      "vix": 22.59,
      "vix_reason": "vix_reduced_to_50pct (22.6 >= 20)",
      "indicators": {
        "ema_fast": 88.92,
        "ema_slow": 89.38,
        "diff": -0.4542
      }
    },
    {
      "timestamp": "2026-06-12T12:47:09.316104-04:00",
      "strategy": "ema_crossover",
      "strategy_type": "daily",
      "vix_type": "TREND",
      "symbol": "V",
      "signal": "hold",
      "price": 323.83,
      "atr": 6.8306,
      "qty": 0,
      "stop_price": null,
      "tp_price": null,
      "executed": false,
      "skip_reason": "no_signal",
      "order_id": null,
      "vix": 22.59,
      "vix_reason": "vix_reduced_to_50pct (22.6 >= 20)",
      "indicators": {
        "ema_fast": 322.43,
        "ema_slow": 322.24,
        "diff": 0.1843
      }
    },
    {
      "timestamp": "2026-06-12T12:47:09.316104-04:00",
      "strategy": "ema_crossover",
      "strategy_type": "daily",
      "vix_type": "TREND",
      "symbol": "BAC",
      "signal": "hold",
      "price": 55.66,
      "atr": 1.1121,
      "qty": 0,
      "stop_price": null,
      "tp_price": null,
      "executed": false,
      "skip_reason": "no_signal",
      "order_id": null,
      "vix": 22.59,
      "vix_reason": "vix_reduced_to_50pct (22.6 >= 20)",
      "indicators": {
        "ema_fast": 53.73,
        "ema_slow": 52.82,
        "diff": 0.9091
      }
    },
    {
      "timestamp": "2026-06-12T12:47:09.316104-04:00",
      "strategy": "ema_crossover",
      "strategy_type": "daily",
      "vix_type": "TREND",
      "symbol": "XLV",
      "signal": "hold",
      "price": 153.86,
      "atr": 2.3209,
      "qty": 0,
      "stop_price": null,
      "tp_price": null,
      "executed": false,
      "skip_reason": "no_signal",
      "order_id": null,
      "vix": 22.59,
      "vix_reason": "vix_reduced_to_50pct (22.6 >= 20)",
      "indicators": {
        "ema_fast": 151.69,
        "ema_slow": 149.8,
        "diff": 1.8882
      }
    },
    {
      "timestamp": "2026-06-12T12:47:09.316104-04:00",
      "strategy": "ema_crossover",
      "strategy_type": "daily",
      "vix_type": "TREND",
      "symbol": "XOM",
      "signal": "hold",
      "price": 147.92,
      "atr": 3.8585,
      "qty": 0,
      "stop_price": null,
      "tp_price": null,
      "executed": false,
      "skip_reason": "no_signal",
      "order_id": null,
      "vix": 22.59,
      "vix_reason": "vix_reduced_to_50pct (22.6 >= 20)",
      "indicators": {
        "ema_fast": 149.78,
        "ema_slow": 150.88,
        "diff": -1.0941
      }
    }
  ],
  "orders_placed": [],
  "trading_pnl": -123.65,
  "total_deposited": 27768.78,
  "deposit_count": 3
}