{
  "run_timestamp": "2026-07-06T13:45:27.337396-04:00",
  "mode": "live",
  "strategy_mode": "daily",
  "equity": 28747.69,
  "last_equity": 28801.18,
  "buying_power": 102112.12,
  "vix": 15.89,
  "drawdown_pct": 0.54,
  "peak_equity": 28903.5,
  "kill_switch_active": false,
  "positions": [
    "AAPL",
    "NKE",
    "PYPL",
    "SPY"
  ],
  "position_details": [
    {
      "symbol": "AAPL",
      "qty": 9.0,
      "side": "long",
      "avg_entry_price": 312.73,
      "current_price": 312.4,
      "market_value": 2811.6,
      "unrealized_pl": -2.92,
      "unrealized_plpc": -0.104,
      "cost_basis": 2814.53,
      "strategy_type": "daily",
      "entry_strategy": "unknown",
      "watching_strategies": [
        "rsi_macd_combo",
        "macd_crossover",
        "triple_ema",
        "ema_crossover"
      ]
    },
    {
      "symbol": "NKE",
      "qty": 66.0,
      "side": "long",
      "avg_entry_price": 42.99,
      "current_price": 43.03,
      "market_value": 2840.31,
      "unrealized_pl": 3.01,
      "unrealized_plpc": 0.106,
      "cost_basis": 2837.3,
      "strategy_type": "daily",
      "entry_strategy": "unknown",
      "watching_strategies": [
        "rsi_macd_combo",
        "macd_crossover",
        "triple_ema",
        "ema_crossover"
      ]
    },
    {
      "symbol": "PYPL",
      "qty": 63.0,
      "side": "long",
      "avg_entry_price": 45.02,
      "current_price": 44.92,
      "market_value": 2830.28,
      "unrealized_pl": -5.77,
      "unrealized_plpc": -0.203,
      "cost_basis": 2836.05,
      "strategy_type": "daily",
      "entry_strategy": "unknown",
      "watching_strategies": [
        "rsi_macd_combo",
        "macd_crossover",
        "triple_ema",
        "ema_crossover"
      ]
    },
    {
      "symbol": "SPY",
      "qty": 3.0,
      "side": "long",
      "avg_entry_price": 750.6,
      "current_price": 749.95,
      "market_value": 2249.85,
      "unrealized_pl": -1.95,
      "unrealized_plpc": -0.086,
      "cost_basis": 2251.8,
      "strategy_type": "daily",
      "entry_strategy": "unknown",
      "watching_strategies": [
        "rsi_macd_combo",
        "macd_crossover",
        "triple_ema",
        "ema_crossover"
      ]
    }
  ],
  "signals": [
    {
      "timestamp": "2026-07-06T13:45:27.337396-04:00",
      "strategy": "rsi_macd_combo",
      "strategy_type": "daily",
      "vix_type": "COMBO",
      "symbol": "AAPL",
      "signal": "hold",
      "price": 312.4,
      "atr": 9.3796,
      "qty": 0,
      "stop_price": null,
      "tp_price": null,
      "executed": false,
      "skip_reason": "no_signal",
      "order_id": null,
      "vix": 15.89,
      "vix_reason": "vix_clear",
      "indicators": {
        "rsi": 62.97,
        "macd": 0.7957,
        "macd_sig": -0.6596,
        "macd_hist": 1.4553
      }
    },
    {
      "timestamp": "2026-07-06T13:45:27.337396-04:00",
      "strategy": "rsi_macd_combo",
      "strategy_type": "daily",
      "vix_type": "COMBO",
      "symbol": "NKE",
      "signal": "hold",
      "price": 43.06,
      "atr": 1.6473,
      "qty": 0,
      "stop_price": null,
      "tp_price": null,
      "executed": false,
      "skip_reason": "no_signal",
      "order_id": null,
      "vix": 15.89,
      "vix_reason": "vix_clear",
      "indicators": {
        "rsi": 48.41,
        "macd": -0.5374,
        "macd_sig": -0.5815,
        "macd_hist": 0.044
      }
    },
    {
      "timestamp": "2026-07-06T13:45:27.337396-04:00",
      "strategy": "rsi_macd_combo",
      "strategy_type": "daily",
      "vix_type": "COMBO",
      "symbol": "PYPL",
      "signal": "hold",
      "price": 44.96,
      "atr": 1.4627,
      "qty": 0,
      "stop_price": null,
      "tp_price": null,
      "executed": false,
      "skip_reason": "no_signal",
      "order_id": null,
      "vix": 15.89,
      "vix_reason": "vix_clear",
      "indicators": {
        "rsi": 57.0,
        "macd": 0.1141,
        "macd_sig": -0.3481,
        "macd_hist": 0.4622
      }
    },
    {
      "timestamp": "2026-07-06T13:45:27.337396-04:00",
      "strategy": "rsi_macd_combo",
      "strategy_type": "daily",
      "vix_type": "COMBO",
      "symbol": "SPY",
      "signal": "hold",
      "price": 750.08,
      "atr": 9.9824,
      "qty": 0,
      "stop_price": null,
      "tp_price": null,
      "executed": false,
      "skip_reason": "no_signal",
      "order_id": null,
      "vix": 15.89,
      "vix_reason": "vix_clear",
      "indicators": {
        "rsi": 57.18,
        "macd": 1.875,
        "macd_sig": 1.657,
        "macd_hist": 0.218
      }
    },
    {
      "timestamp": "2026-07-06T13:45:27.337396-04:00",
      "strategy": "rsi_macd_combo",
      "strategy_type": "daily",
      "vix_type": "COMBO",
      "symbol": "QQQ",
      "signal": "hold",
      "price": 721.62,
      "atr": 16.8119,
      "qty": 0,
      "stop_price": null,
      "tp_price": null,
      "executed": false,
      "skip_reason": "no_signal",
      "order_id": null,
      "vix": 15.89,
      "vix_reason": "vix_clear",
      "indicators": {
        "rsi": 51.27,
        "macd": 2.9597,
        "macd_sig": 4.865,
        "macd_hist": -1.9053
      }
    },
    {
      "timestamp": "2026-07-06T13:45:27.337396-04:00",
      "strategy": "rsi_macd_combo",
      "strategy_type": "daily",
      "vix_type": "COMBO",
      "symbol": "IWM",
      "signal": "hold",
      "price": 299.53,
      "atr": 4.93,
      "qty": 0,
      "stop_price": null,
      "tp_price": null,
      "executed": false,
      "skip_reason": "no_signal",
      "order_id": null,
      "vix": 15.89,
      "vix_reason": "vix_clear",
      "indicators": {
        "rsi": 60.39,
        "macd": 4.0105,
        "macd_sig": 4.0333,
        "macd_hist": -0.0227
      }
    },
    {
      "timestamp": "2026-07-06T13:45:27.337396-04:00",
      "strategy": "rsi_macd_combo",
      "strategy_type": "daily",
      "vix_type": "COMBO",
      "symbol": "GLD",
      "signal": "hold",
      "price": 381.56,
      "atr": 7.467,
      "qty": 0,
      "stop_price": null,
      "tp_price": null,
      "executed": false,
      "skip_reason": "no_signal",
      "order_id": null,
      "vix": 15.89,
      "vix_reason": "vix_clear",
      "indicators": {
        "rsi": 44.84,
        "macd": -9.5247,
        "macd_sig": -10.5621,
        "macd_hist": 1.0374
      }
    },
    {
      "timestamp": "2026-07-06T13:45:27.337396-04:00",
      "strategy": "rsi_macd_combo",
      "strategy_type": "daily",
      "vix_type": "COMBO",
      "symbol": "XLK",
      "signal": "hold",
      "price": 183.5,
      "atr": 6.163,
      "qty": 0,
      "stop_price": null,
      "tp_price": null,
      "executed": false,
      "skip_reason": "no_signal",
      "order_id": null,
      "vix": 15.89,
      "vix_reason": "vix_clear",
      "indicators": {
        "rsi": 50.08,
        "macd": 1.257,
        "macd_sig": 2.3585,
        "macd_hist": -1.1015
      }
    },
    {
      "timestamp": "2026-07-06T13:45:27.337396-04:00",
      "strategy": "rsi_macd_combo",
      "strategy_type": "daily",
      "vix_type": "COMBO",
      "symbol": "XLE",
      "signal": "hold",
      "price": 53.28,
      "atr": 0.9638,
      "qty": 0,
      "stop_price": null,
      "tp_price": null,
      "executed": false,
      "skip_reason": "no_signal",
      "order_id": null,
      "vix": 15.89,
      "vix_reason": "vix_clear",
      "indicators": {
        "rsi": 36.91,
        "macd": -1.2079,
        "macd_sig": -1.0852,
        "macd_hist": -0.1227
      }
    },
    {
      "timestamp": "2026-07-06T13:45:27.337396-04:00",
      "strategy": "rsi_macd_combo",
      "strategy_type": "daily",
      "vix_type": "COMBO",
      "symbol": "XLF",
      "signal": "hold",
      "price": 56.02,
      "atr": 0.7587,
      "qty": 0,
      "stop_price": null,
      "tp_price": null,
      "executed": false,
      "skip_reason": "no_signal",
      "order_id": null,
      "vix": 15.89,
      "vix_reason": "vix_clear",
      "indicators": {
        "rsi": 75.55,
        "macd": 0.8165,
        "macd_sig": 0.6254,
        "macd_hist": 0.1912
      }
    },
    {
      "timestamp": "2026-07-06T13:45:27.337396-04:00",
      "strategy": "rsi_macd_combo",
      "strategy_type": "daily",
      "vix_type": "COMBO",
      "symbol": "PANW",
      "signal": "hold",
      "price": 356.49,
      "atr": 15.8366,
      "qty": 0,
      "stop_price": null,
      "tp_price": null,
      "executed": false,
      "skip_reason": "no_signal",
      "order_id": null,
      "vix": 15.89,
      "vix_reason": "vix_clear",
      "indicators": {
        "rsi": 79.89,
        "macd": 25.7441,
        "macd_sig": 20.604,
        "macd_hist": 5.1402
      }
    },
    {
      "timestamp": "2026-07-06T13:45:27.337396-04:00",
      "strategy": "rsi_macd_combo",
      "strategy_type": "daily",
      "vix_type": "COMBO",
      "symbol": "INTC",
      "signal": "hold",
      "price": 122.73,
      "atr": 10.7135,
      "qty": 0,
      "stop_price": null,
      "tp_price": null,
      "executed": false,
      "skip_reason": "no_signal",
      "order_id": null,
      "vix": 15.89,
      "vix_reason": "vix_clear",
      "indicators": {
        "rsi": 50.69,
        "macd": 4.7321,
        "macd_sig": 6.2049,
        "macd_hist": -1.4728
      }
    },
    {
      "timestamp": "2026-07-06T13:45:27.337396-04:00",
      "strategy": "rsi_macd_combo",
      "strategy_type": "daily",
      "vix_type": "COMBO",
      "symbol": "AMD",
      "signal": "hold",
      "price": 553.72,
      "atr": 40.0685,
      "qty": 0,
      "stop_price": null,
      "tp_price": null,
      "executed": false,
      "skip_reason": "no_signal",
      "order_id": null,
      "vix": 15.89,
      "vix_reason": "vix_clear",
      "indicators": {
        "rsi": 57.57,
        "macd": 23.3852,
        "macd_sig": 26.0001,
        "macd_hist": -2.6149
      }
    },
    {
      "timestamp": "2026-07-06T13:45:27.337396-04:00",
      "strategy": "rsi_macd_combo",
      "strategy_type": "daily",
      "vix_type": "COMBO",
      "symbol": "MRVL",
      "signal": "hold",
      "price": 249.43,
      "atr": 26.7322,
      "qty": 0,
      "stop_price": null,
      "tp_price": null,
      "executed": false,
      "skip_reason": "no_signal",
      "order_id": null,
      "vix": 15.89,
      "vix_reason": "vix_clear",
      "indicators": {
        "rsi": 47.51,
        "macd": 10.0869,
        "macd_sig": 18.6193,
        "macd_hist": -8.5324
      }
    },
    {
      "timestamp": "2026-07-06T13:45:27.337396-04:00",
      "strategy": "rsi_macd_combo",
      "strategy_type": "daily",
      "vix_type": "COMBO",
      "symbol": "HOOD",
      "signal": "hold",
      "price": 116.42,
      "atr": 7.1935,
      "qty": 0,
      "stop_price": null,
      "tp_price": null,
      "executed": false,
      "skip_reason": "no_signal",
      "order_id": null,
      "vix": 15.89,
      "vix_reason": "vix_clear",
      "indicators": {
        "rsi": 69.18,
        "macd": 6.7152,
        "macd_sig": 5.5536,
        "macd_hist": 1.1616
      }
    },
    {
      "timestamp": "2026-07-06T13:45:27.337396-04:00",
      "strategy": "rsi_macd_combo",
      "strategy_type": "daily",
      "vix_type": "COMBO",
      "symbol": "AMAT",
      "signal": "hold",
      "price": 593.32,
      "atr": 53.77,
      "qty": 0,
      "stop_price": null,
      "tp_price": null,
      "executed": false,
      "skip_reason": "no_signal",
      "order_id": null,
      "vix": 15.89,
      "vix_reason": "vix_clear",
      "indicators": {
        "rsi": 52.73,
        "macd": 45.1289,
        "macd_sig": 49.5326,
        "macd_hist": -4.4037
      }
    },
    {
      "timestamp": "2026-07-06T13:45:27.337396-04:00",
      "strategy": "rsi_macd_combo",
      "strategy_type": "daily",
      "vix_type": "COMBO",
      "symbol": "SNOW",
      "signal": "hold",
      "price": 262.41,
      "atr": 12.0725,
      "qty": 0,
      "stop_price": null,
      "tp_price": null,
      "executed": false,
      "skip_reason": "no_signal",
      "order_id": null,
      "vix": 15.89,
      "vix_reason": "vix_clear",
      "indicators": {
        "rsi": 69.35,
        "macd": 14.2694,
        "macd_sig": 13.9478,
        "macd_hist": 0.3216
      }
    },
    {
      "timestamp": "2026-07-06T13:45:27.337396-04:00",
      "strategy": "rsi_macd_combo",
      "strategy_type": "daily",
      "vix_type": "COMBO",
      "symbol": "LRCX",
      "signal": "hold",
      "price": 350.99,
      "atr": 31.0764,
      "qty": 0,
      "stop_price": null,
      "tp_price": null,
      "executed": false,
      "skip_reason": "no_signal",
      "order_id": null,
      "vix": 15.89,
      "vix_reason": "vix_clear",
      "indicators": {
        "rsi": 48.35,
        "macd": 16.976,
        "macd_sig": 22.5442,
        "macd_hist": -5.5682
      }
    },
    {
      "timestamp": "2026-07-06T13:45:27.337396-04:00",
      "strategy": "rsi_macd_combo",
      "strategy_type": "daily",
      "vix_type": "COMBO",
      "symbol": "BAC",
      "signal": "hold",
      "price": 59.72,
      "atr": 1.1708,
      "qty": 0,
      "stop_price": null,
      "tp_price": null,
      "executed": false,
      "skip_reason": "no_signal",
      "order_id": null,
      "vix": 15.89,
      "vix_reason": "vix_clear",
      "indicators": {
        "rsi": 73.37,
        "macd": 1.5574,
        "macd_sig": 1.4385,
        "macd_hist": 0.1189
      }
    },
    {
      "timestamp": "2026-07-06T13:45:27.337396-04:00",
      "strategy": "rsi_macd_combo",
      "strategy_type": "daily",
      "vix_type": "COMBO",
      "symbol": "V",
      "signal": "hold",
      "price": 356.82,
      "atr": 9.2199,
      "qty": 0,
      "stop_price": null,
      "tp_price": null,
      "executed": false,
      "skip_reason": "no_signal",
      "order_id": null,
      "vix": 15.89,
      "vix_reason": "vix_clear",
      "indicators": {
        "rsi": 70.64,
        "macd": 7.8779,
        "macd_sig": 4.6636,
        "macd_hist": 3.2143
      }
    },
    {
      "timestamp": "2026-07-06T13:45:27.337396-04:00",
      "strategy": "rsi_macd_combo",
      "strategy_type": "daily",
      "vix_type": "COMBO",
      "symbol": "MS",
      "signal": "hold",
      "price": 220.29,
      "atr": 5.9163,
      "qty": 0,
      "stop_price": null,
      "tp_price": null,
      "executed": false,
      "skip_reason": "no_signal",
      "order_id": null,
      "vix": 15.89,
      "vix_reason": "vix_clear",
      "indicators": {
        "rsi": 58.85,
        "macd": 3.0467,
        "macd_sig": 4.4606,
        "macd_hist": -1.4138
      }
    },
    {
      "timestamp": "2026-07-06T13:45:27.337396-04:00",
      "strategy": "rsi_macd_combo",
      "strategy_type": "daily",
      "vix_type": "COMBO",
      "symbol": "SOFI",
      "signal": "hold",
      "price": 18.68,
      "atr": 0.9413,
      "qty": 0,
      "stop_price": null,
      "tp_price": null,
      "executed": false,
      "skip_reason": "no_signal",
      "order_id": null,
      "vix": 15.89,
      "vix_reason": "vix_clear",
      "indicators": {
        "rsi": 61.81,
        "macd": 0.4341,
        "macd_sig": 0.3041,
        "macd_hist": 0.13
      }
    },
    {
      "timestamp": "2026-07-06T13:45:27.337396-04:00",
      "strategy": "rsi_macd_combo",
      "strategy_type": "daily",
      "vix_type": "COMBO",
      "symbol": "XLV",
      "signal": "hold",
      "price": 162.15,
      "atr": 2.8515,
      "qty": 0,
      "stop_price": null,
      "tp_price": null,
      "executed": false,
      "skip_reason": "no_signal",
      "order_id": null,
      "vix": 15.89,
      "vix_reason": "vix_clear",
      "indicators": {
        "rsi": 67.53,
        "macd": 3.2407,
        "macd_sig": 2.3829,
        "macd_hist": 0.8578
      }
    },
    {
      "timestamp": "2026-07-06T13:45:27.337396-04:00",
      "strategy": "rsi_macd_combo",
      "strategy_type": "daily",
      "vix_type": "COMBO",
      "symbol": "MRK",
      "signal": "hold",
      "price": 126.73,
      "atr": 3.5509,
      "qty": 0,
      "stop_price": null,
      "tp_price": null,
      "executed": false,
      "skip_reason": "no_signal",
      "order_id": null,
      "vix": 15.89,
      "vix_reason": "vix_clear",
      "indicators": {
        "rsi": 59.63,
        "macd": 3.0152,
        "macd_sig": 2.1806,
        "macd_hist": 0.8347
      }
    },
    {
      "timestamp": "2026-07-06T13:45:27.337396-04:00",
      "strategy": "rsi_macd_combo",
      "strategy_type": "daily",
      "vix_type": "COMBO",
      "symbol": "XLY",
      "signal": "hold",
      "price": 117.78,
      "atr": 2.21,
      "qty": 0,
      "stop_price": null,
      "tp_price": null,
      "executed": false,
      "skip_reason": "no_signal",
      "order_id": null,
      "vix": 15.89,
      "vix_reason": "vix_clear",
      "indicators": {
        "rsi": 53.36,
        "macd": -0.0585,
        "macd_sig": -0.3564,
        "macd_hist": 0.2979
      }
    },
    {
      "timestamp": "2026-07-06T13:45:27.337396-04:00",
      "strategy": "rsi_macd_combo",
      "strategy_type": "daily",
      "vix_type": "COMBO",
      "symbol": "XLI",
      "signal": "hold",
      "price": 185.33,
      "atr": 3.2069,
      "qty": 0,
      "stop_price": null,
      "tp_price": null,
      "executed": false,
      "skip_reason": "no_signal",
      "order_id": null,
      "vix": 15.89,
      "vix_reason": "vix_clear",
      "indicators": {
        "rsi": 62.45,
        "macd": 2.8452,
        "macd_sig": 2.4504,
        "macd_hist": 0.3948
      }
    },
    {
      "timestamp": "2026-07-06T13:45:27.337396-04:00",
      "strategy": "rsi_macd_combo",
      "strategy_type": "daily",
      "vix_type": "COMBO",
      "symbol": "ARKK",
      "signal": "hold",
      "price": 83.4,
      "atr": 2.6954,
      "qty": 0,
      "stop_price": null,
      "tp_price": null,
      "executed": false,
      "skip_reason": "no_signal",
      "order_id": null,
      "vix": 15.89,
      "vix_reason": "vix_clear",
      "indicators": {
        "rsi": 63.38,
        "macd": 1.1945,
        "macd_sig": 0.6599,
        "macd_hist": 0.5347
      }
    },
    {
      "timestamp": "2026-07-06T13:45:27.337396-04:00",
      "strategy": "rsi_macd_combo",
      "strategy_type": "daily",
      "vix_type": "COMBO",
      "symbol": "DIS",
      "signal": "hold",
      "price": 97.59,
      "atr": 2.4861,
      "qty": 0,
      "stop_price": null,
      "tp_price": null,
      "executed": false,
      "skip_reason": "no_signal",
      "order_id": null,
      "vix": 15.89,
      "vix_reason": "vix_clear",
      "indicators": {
        "rsi": 43.29,
        "macd": -1.1539,
        "macd_sig": -0.865,
        "macd_hist": -0.2888
      }
    },
    {
      "timestamp": "2026-07-06T13:45:27.337396-04:00",
      "strategy": "rsi_macd_combo",
      "strategy_type": "daily",
      "vix_type": "COMBO",
      "symbol": "GOOGL",
      "signal": "hold",
      "price": 364.46,
      "atr": 10.918,
      "qty": 0,
      "stop_price": null,
      "tp_price": null,
      "executed": false,
      "skip_reason": "no_signal",
      "order_id": null,
      "vix": 15.89,
      "vix_reason": "vix_clear",
      "indicators": {
        "rsi": 52.45,
        "macd": -3.4125,
        "macd_sig": -4.6084,
        "macd_hist": 1.1959
      }
    },
    {
      "timestamp": "2026-07-06T13:45:27.337396-04:00",
      "strategy": "rsi_macd_combo",
      "strategy_type": "daily",
      "vix_type": "COMBO",
      "symbol": "UBER",
      "signal": "hold",
      "price": 73.43,
      "atr": 2.7015,
      "qty": 0,
      "stop_price": null,
      "tp_price": null,
      "executed": false,
      "skip_reason": "no_signal",
      "order_id": null,
      "vix": 15.89,
      "vix_reason": "vix_clear",
      "indicators": {
        "rsi": 51.89,
        "macd": 0.3532,
        "macd_sig": 0.0378,
        "macd_hist": 0.3154
      }
    },
    {
      "timestamp": "2026-07-06T13:45:27.337396-04:00",
      "strategy": "macd_crossover",
      "strategy_type": "daily",
      "vix_type": "TREND",
      "symbol": "AAPL",
      "signal": "hold",
      "price": 312.4,
      "atr": 9.3796,
      "qty": 0,
      "stop_price": null,
      "tp_price": null,
      "executed": false,
      "skip_reason": "no_signal",
      "order_id": null,
      "vix": 15.89,
      "vix_reason": "vix_clear",
      "indicators": {
        "macd": 0.7957,
        "macd_sig": -0.6596,
        "macd_hist": 1.4553
      }
    },
    {
      "timestamp": "2026-07-06T13:45:27.337396-04:00",
      "strategy": "macd_crossover",
      "strategy_type": "daily",
      "vix_type": "TREND",
      "symbol": "NKE",
      "signal": "buy",
      "price": 43.06,
      "atr": 1.6473,
      "qty": 0,
      "stop_price": null,
      "tp_price": null,
      "executed": false,
      "skip_reason": "already_in_position",
      "order_id": null,
      "vix": 15.89,
      "vix_reason": "vix_clear",
      "indicators": {
        "macd": -0.5374,
        "macd_sig": -0.5815,
        "macd_hist": 0.044
      }
    },
    {
      "timestamp": "2026-07-06T13:45:27.337396-04:00",
      "strategy": "macd_crossover",
      "strategy_type": "daily",
      "vix_type": "TREND",
      "symbol": "PYPL",
      "signal": "hold",
      "price": 44.96,
      "atr": 1.4627,
      "qty": 0,
      "stop_price": null,
      "tp_price": null,
      "executed": false,
      "skip_reason": "no_signal",
      "order_id": null,
      "vix": 15.89,
      "vix_reason": "vix_clear",
      "indicators": {
        "macd": 0.1141,
        "macd_sig": -0.3481,
        "macd_hist": 0.4622
      }
    },
    {
      "timestamp": "2026-07-06T13:45:27.337396-04:00",
      "strategy": "macd_crossover",
      "strategy_type": "daily",
      "vix_type": "TREND",
      "symbol": "SPY",
      "signal": "buy",
      "price": 750.08,
      "atr": 9.9824,
      "qty": 0,
      "stop_price": null,
      "tp_price": null,
      "executed": false,
      "skip_reason": "already_in_position",
      "order_id": null,
      "vix": 15.89,
      "vix_reason": "vix_clear",
      "indicators": {
        "macd": 1.875,
        "macd_sig": 1.657,
        "macd_hist": 0.218
      }
    },
    {
      "timestamp": "2026-07-06T13:45:27.337396-04:00",
      "strategy": "macd_crossover",
      "strategy_type": "daily",
      "vix_type": "TREND",
      "symbol": "QQQ",
      "signal": "hold",
      "price": 721.62,
      "atr": 16.8119,
      "qty": 0,
      "stop_price": null,
      "tp_price": null,
      "executed": false,
      "skip_reason": "no_signal",
      "order_id": null,
      "vix": 15.89,
      "vix_reason": "vix_clear",
      "indicators": {
        "macd": 2.9597,
        "macd_sig": 4.865,
        "macd_hist": -1.9053
      }
    },
    {
      "timestamp": "2026-07-06T13:45:27.337396-04:00",
      "strategy": "macd_crossover",
      "strategy_type": "daily",
      "vix_type": "TREND",
      "symbol": "IWM",
      "signal": "sell",
      "price": 299.53,
      "atr": 4.93,
      "qty": 0,
      "stop_price": null,
      "tp_price": null,
      "executed": false,
      "skip_reason": "no_position_to_sell",
      "order_id": null,
      "vix": 15.89,
      "vix_reason": "vix_clear",
      "indicators": {
        "macd": 4.0105,
        "macd_sig": 4.0333,
        "macd_hist": -0.0227
      }
    },
    {
      "timestamp": "2026-07-06T13:45:27.337396-04:00",
      "strategy": "macd_crossover",
      "strategy_type": "daily",
      "vix_type": "TREND",
      "symbol": "GLD",
      "signal": "hold",
      "price": 381.56,
      "atr": 7.467,
      "qty": 0,
      "stop_price": null,
      "tp_price": null,
      "executed": false,
      "skip_reason": "no_signal",
      "order_id": null,
      "vix": 15.89,
      "vix_reason": "vix_clear",
      "indicators": {
        "macd": -9.5247,
        "macd_sig": -10.5621,
        "macd_hist": 1.0374
      }
    },
    {
      "timestamp": "2026-07-06T13:45:27.337396-04:00",
      "strategy": "macd_crossover",
      "strategy_type": "daily",
      "vix_type": "TREND",
      "symbol": "XLK",
      "signal": "hold",
      "price": 183.5,
      "atr": 6.163,
      "qty": 0,
      "stop_price": null,
      "tp_price": null,
      "executed": false,
      "skip_reason": "no_signal",
      "order_id": null,
      "vix": 15.89,
      "vix_reason": "vix_clear",
      "indicators": {
        "macd": 1.257,
        "macd_sig": 2.3585,
        "macd_hist": -1.1015
      }
    },
    {
      "timestamp": "2026-07-06T13:45:27.337396-04:00",
      "strategy": "macd_crossover",
      "strategy_type": "daily",
      "vix_type": "TREND",
      "symbol": "XLE",
      "signal": "hold",
      "price": 53.28,
      "atr": 0.9638,
      "qty": 0,
      "stop_price": null,
      "tp_price": null,
      "executed": false,
      "skip_reason": "no_signal",
      "order_id": null,
      "vix": 15.89,
      "vix_reason": "vix_clear",
      "indicators": {
        "macd": -1.2079,
        "macd_sig": -1.0852,
        "macd_hist": -0.1227
      }
    },
    {
      "timestamp": "2026-07-06T13:45:27.337396-04:00",
      "strategy": "macd_crossover",
      "strategy_type": "daily",
      "vix_type": "TREND",
      "symbol": "XLF",
      "signal": "hold",
      "price": 56.02,
      "atr": 0.7587,
      "qty": 0,
      "stop_price": null,
      "tp_price": null,
      "executed": false,
      "skip_reason": "no_signal",
      "order_id": null,
      "vix": 15.89,
      "vix_reason": "vix_clear",
      "indicators": {
        "macd": 0.8165,
        "macd_sig": 0.6254,
        "macd_hist": 0.1912
      }
    },
    {
      "timestamp": "2026-07-06T13:45:27.337396-04:00",
      "strategy": "macd_crossover",
      "strategy_type": "daily",
      "vix_type": "TREND",
      "symbol": "PANW",
      "signal": "hold",
      "price": 356.49,
      "atr": 15.8366,
      "qty": 0,
      "stop_price": null,
      "tp_price": null,
      "executed": false,
      "skip_reason": "no_signal",
      "order_id": null,
      "vix": 15.89,
      "vix_reason": "vix_clear",
      "indicators": {
        "macd": 25.7441,
        "macd_sig": 20.604,
        "macd_hist": 5.1402
      }
    },
    {
      "timestamp": "2026-07-06T13:45:27.337396-04:00",
      "strategy": "macd_crossover",
      "strategy_type": "daily",
      "vix_type": "TREND",
      "symbol": "INTC",
      "signal": "hold",
      "price": 122.73,
      "atr": 10.7135,
      "qty": 0,
      "stop_price": null,
      "tp_price": null,
      "executed": false,
      "skip_reason": "no_signal",
      "order_id": null,
      "vix": 15.89,
      "vix_reason": "vix_clear",
      "indicators": {
        "macd": 4.7321,
        "macd_sig": 6.2049,
        "macd_hist": -1.4728
      }
    },
    {
      "timestamp": "2026-07-06T13:45:27.337396-04:00",
      "strategy": "macd_crossover",
      "strategy_type": "daily",
      "vix_type": "TREND",
      "symbol": "AMD",
      "signal": "hold",
      "price": 553.72,
      "atr": 40.0685,
      "qty": 0,
      "stop_price": null,
      "tp_price": null,
      "executed": false,
      "skip_reason": "no_signal",
      "order_id": null,
      "vix": 15.89,
      "vix_reason": "vix_clear",
      "indicators": {
        "macd": 23.3852,
        "macd_sig": 26.0001,
        "macd_hist": -2.6149
      }
    },
    {
      "timestamp": "2026-07-06T13:45:27.337396-04:00",
      "strategy": "macd_crossover",
      "strategy_type": "daily",
      "vix_type": "TREND",
      "symbol": "MRVL",
      "signal": "hold",
      "price": 249.43,
      "atr": 26.7322,
      "qty": 0,
      "stop_price": null,
      "tp_price": null,
      "executed": false,
      "skip_reason": "no_signal",
      "order_id": null,
      "vix": 15.89,
      "vix_reason": "vix_clear",
      "indicators": {
        "macd": 10.0869,
        "macd_sig": 18.6193,
        "macd_hist": -8.5324
      }
    },
    {
      "timestamp": "2026-07-06T13:45:27.337396-04:00",
      "strategy": "macd_crossover",
      "strategy_type": "daily",
      "vix_type": "TREND",
      "symbol": "HOOD",
      "signal": "hold",
      "price": 116.42,
      "atr": 7.1935,
      "qty": 0,
      "stop_price": null,
      "tp_price": null,
      "executed": false,
      "skip_reason": "no_signal",
      "order_id": null,
      "vix": 15.89,
      "vix_reason": "vix_clear",
      "indicators": {
        "macd": 6.7152,
        "macd_sig": 5.5536,
        "macd_hist": 1.1616
      }
    },
    {
      "timestamp": "2026-07-06T13:45:27.337396-04:00",
      "strategy": "macd_crossover",
      "strategy_type": "daily",
      "vix_type": "TREND",
      "symbol": "AMAT",
      "signal": "sell",
      "price": 593.32,
      "atr": 53.77,
      "qty": 0,
      "stop_price": null,
      "tp_price": null,
      "executed": false,
      "skip_reason": "no_position_to_sell",
      "order_id": null,
      "vix": 15.89,
      "vix_reason": "vix_clear",
      "indicators": {
        "macd": 45.1289,
        "macd_sig": 49.5326,
        "macd_hist": -4.4037
      }
    },
    {
      "timestamp": "2026-07-06T13:45:27.337396-04:00",
      "strategy": "macd_crossover",
      "strategy_type": "daily",
      "vix_type": "TREND",
      "symbol": "SNOW",
      "signal": "hold",
      "price": 262.41,
      "atr": 12.0725,
      "qty": 0,
      "stop_price": null,
      "tp_price": null,
      "executed": false,
      "skip_reason": "no_signal",
      "order_id": null,
      "vix": 15.89,
      "vix_reason": "vix_clear",
      "indicators": {
        "macd": 14.2694,
        "macd_sig": 13.9478,
        "macd_hist": 0.3216
      }
    },
    {
      "timestamp": "2026-07-06T13:45:27.337396-04:00",
      "strategy": "macd_crossover",
      "strategy_type": "daily",
      "vix_type": "TREND",
      "symbol": "LRCX",
      "signal": "hold",
      "price": 350.99,
      "atr": 31.0764,
      "qty": 0,
      "stop_price": null,
      "tp_price": null,
      "executed": false,
      "skip_reason": "no_signal",
      "order_id": null,
      "vix": 15.89,
      "vix_reason": "vix_clear",
      "indicators": {
        "macd": 16.976,
        "macd_sig": 22.5442,
        "macd_hist": -5.5682
      }
    },
    {
      "timestamp": "2026-07-06T13:45:27.337396-04:00",
      "strategy": "macd_crossover",
      "strategy_type": "daily",
      "vix_type": "TREND",
      "symbol": "BAC",
      "signal": "hold",
      "price": 59.72,
      "atr": 1.1708,
      "qty": 0,
      "stop_price": null,
      "tp_price": null,
      "executed": false,
      "skip_reason": "no_signal",
      "order_id": null,
      "vix": 15.89,
      "vix_reason": "vix_clear",
      "indicators": {
        "macd": 1.5574,
        "macd_sig": 1.4385,
        "macd_hist": 0.1189
      }
    },
    {
      "timestamp": "2026-07-06T13:45:27.337396-04:00",
      "strategy": "macd_crossover",
      "strategy_type": "daily",
      "vix_type": "TREND",
      "symbol": "V",
      "signal": "hold",
      "price": 356.82,
      "atr": 9.2199,
      "qty": 0,
      "stop_price": null,
      "tp_price": null,
      "executed": false,
      "skip_reason": "no_signal",
      "order_id": null,
      "vix": 15.89,
      "vix_reason": "vix_clear",
      "indicators": {
        "macd": 7.8779,
        "macd_sig": 4.6636,
        "macd_hist": 3.2143
      }
    },
    {
      "timestamp": "2026-07-06T13:45:27.337396-04:00",
      "strategy": "macd_crossover",
      "strategy_type": "daily",
      "vix_type": "TREND",
      "symbol": "MS",
      "signal": "hold",
      "price": 220.29,
      "atr": 5.9163,
      "qty": 0,
      "stop_price": null,
      "tp_price": null,
      "executed": false,
      "skip_reason": "no_signal",
      "order_id": null,
      "vix": 15.89,
      "vix_reason": "vix_clear",
      "indicators": {
        "macd": 3.0467,
        "macd_sig": 4.4606,
        "macd_hist": -1.4138
      }
    },
    {
      "timestamp": "2026-07-06T13:45:27.337396-04:00",
      "strategy": "macd_crossover",
      "strategy_type": "daily",
      "vix_type": "TREND",
      "symbol": "SOFI",
      "signal": "hold",
      "price": 18.68,
      "atr": 0.9413,
      "qty": 0,
      "stop_price": null,
      "tp_price": null,
      "executed": false,
      "skip_reason": "no_signal",
      "order_id": null,
      "vix": 15.89,
      "vix_reason": "vix_clear",
      "indicators": {
        "macd": 0.4341,
        "macd_sig": 0.3041,
        "macd_hist": 0.13
      }
    },
    {
      "timestamp": "2026-07-06T13:45:27.337396-04:00",
      "strategy": "macd_crossover",
      "strategy_type": "daily",
      "vix_type": "TREND",
      "symbol": "XLV",
      "signal": "hold",
      "price": 162.15,
      "atr": 2.8515,
      "qty": 0,
      "stop_price": null,
      "tp_price": null,
      "executed": false,
      "skip_reason": "no_signal",
      "order_id": null,
      "vix": 15.89,
      "vix_reason": "vix_clear",
      "indicators": {
        "macd": 3.2407,
        "macd_sig": 2.3829,
        "macd_hist": 0.8578
      }
    },
    {
      "timestamp": "2026-07-06T13:45:27.337396-04:00",
      "strategy": "macd_crossover",
      "strategy_type": "daily",
      "vix_type": "TREND",
      "symbol": "MRK",
      "signal": "hold",
      "price": 126.73,
      "atr": 3.5509,
      "qty": 0,
      "stop_price": null,
      "tp_price": null,
      "executed": false,
      "skip_reason": "no_signal",
      "order_id": null,
      "vix": 15.89,
      "vix_reason": "vix_clear",
      "indicators": {
        "macd": 3.0152,
        "macd_sig": 2.1806,
        "macd_hist": 0.8347
      }
    },
    {
      "timestamp": "2026-07-06T13:45:27.337396-04:00",
      "strategy": "macd_crossover",
      "strategy_type": "daily",
      "vix_type": "TREND",
      "symbol": "XLY",
      "signal": "hold",
      "price": 117.78,
      "atr": 2.21,
      "qty": 0,
      "stop_price": null,
      "tp_price": null,
      "executed": false,
      "skip_reason": "no_signal",
      "order_id": null,
      "vix": 15.89,
      "vix_reason": "vix_clear",
      "indicators": {
        "macd": -0.0585,
        "macd_sig": -0.3564,
        "macd_hist": 0.2979
      }
    },
    {
      "timestamp": "2026-07-06T13:45:27.337396-04:00",
      "strategy": "macd_crossover",
      "strategy_type": "daily",
      "vix_type": "TREND",
      "symbol": "XLI",
      "signal": "hold",
      "price": 185.33,
      "atr": 3.2069,
      "qty": 0,
      "stop_price": null,
      "tp_price": null,
      "executed": false,
      "skip_reason": "no_signal",
      "order_id": null,
      "vix": 15.89,
      "vix_reason": "vix_clear",
      "indicators": {
        "macd": 2.8452,
        "macd_sig": 2.4504,
        "macd_hist": 0.3948
      }
    },
    {
      "timestamp": "2026-07-06T13:45:27.337396-04:00",
      "strategy": "macd_crossover",
      "strategy_type": "daily",
      "vix_type": "TREND",
      "symbol": "ARKK",
      "signal": "hold",
      "price": 83.4,
      "atr": 2.6954,
      "qty": 0,
      "stop_price": null,
      "tp_price": null,
      "executed": false,
      "skip_reason": "no_signal",
      "order_id": null,
      "vix": 15.89,
      "vix_reason": "vix_clear",
      "indicators": {
        "macd": 1.1945,
        "macd_sig": 0.6599,
        "macd_hist": 0.5347
      }
    },
    {
      "timestamp": "2026-07-06T13:45:27.337396-04:00",
      "strategy": "macd_crossover",
      "strategy_type": "daily",
      "vix_type": "TREND",
      "symbol": "DIS",
      "signal": "hold",
      "price": 97.59,
      "atr": 2.4861,
      "qty": 0,
      "stop_price": null,
      "tp_price": null,
      "executed": false,
      "skip_reason": "no_signal",
      "order_id": null,
      "vix": 15.89,
      "vix_reason": "vix_clear",
      "indicators": {
        "macd": -1.1539,
        "macd_sig": -0.865,
        "macd_hist": -0.2888
      }
    },
    {
      "timestamp": "2026-07-06T13:45:27.337396-04:00",
      "strategy": "macd_crossover",
      "strategy_type": "daily",
      "vix_type": "TREND",
      "symbol": "GOOGL",
      "signal": "hold",
      "price": 364.46,
      "atr": 10.918,
      "qty": 0,
      "stop_price": null,
      "tp_price": null,
      "executed": false,
      "skip_reason": "no_signal",
      "order_id": null,
      "vix": 15.89,
      "vix_reason": "vix_clear",
      "indicators": {
        "macd": -3.4125,
        "macd_sig": -4.6084,
        "macd_hist": 1.1959
      }
    },
    {
      "timestamp": "2026-07-06T13:45:27.337396-04:00",
      "strategy": "macd_crossover",
      "strategy_type": "daily",
      "vix_type": "TREND",
      "symbol": "UBER",
      "signal": "hold",
      "price": 73.43,
      "atr": 2.7015,
      "qty": 0,
      "stop_price": null,
      "tp_price": null,
      "executed": false,
      "skip_reason": "no_signal",
      "order_id": null,
      "vix": 15.89,
      "vix_reason": "vix_clear",
      "indicators": {
        "macd": 0.3532,
        "macd_sig": 0.0378,
        "macd_hist": 0.3154
      }
    },
    {
      "timestamp": "2026-07-06T13:45:27.337396-04:00",
      "strategy": "triple_ema",
      "strategy_type": "daily",
      "vix_type": "TREND",
      "symbol": "AAPL",
      "signal": "buy",
      "price": 312.4,
      "atr": 9.3796,
      "qty": 0,
      "stop_price": null,
      "tp_price": null,
      "executed": false,
      "skip_reason": "already_in_position",
      "order_id": null,
      "vix": 15.89,
      "vix_reason": "vix_clear",
      "indicators": {
        "ema_fast": 297.72,
        "ema_mid": 295.91,
        "ema_slow": 290.33
      }
    },
    {
      "timestamp": "2026-07-06T13:45:27.337396-04:00",
      "strategy": "triple_ema",
      "strategy_type": "daily",
      "vix_type": "TREND",
      "symbol": "NKE",
      "signal": "hold",
      "price": 43.06,
      "atr": 1.6473,
      "qty": 0,
      "stop_price": null,
      "tp_price": null,
      "executed": false,
      "skip_reason": "no_signal",
      "order_id": null,
      "vix": 15.89,
      "vix_reason": "vix_clear",
      "indicators": {
        "ema_fast": 42.73,
        "ema_mid": 43.19,
        "ema_slow": 45.06
      }
    },
    {
      "timestamp": "2026-07-06T13:45:27.337396-04:00",
      "strategy": "triple_ema",
      "strategy_type": "daily",
      "vix_type": "TREND",
      "symbol": "PYPL",
      "signal": "hold",
      "price": 44.96,
      "atr": 1.4627,
      "qty": 0,
      "stop_price": null,
      "tp_price": null,
      "executed": false,
      "skip_reason": "no_signal",
      "order_id": null,
      "vix": 15.89,
      "vix_reason": "vix_clear",
      "indicators": {
        "ema_fast": 44.05,
        "ema_mid": 43.52,
        "ema_slow": 44.56
      }
    },
    {
      "timestamp": "2026-07-06T13:45:27.337396-04:00",
      "strategy": "triple_ema",
      "strategy_type": "daily",
      "vix_type": "TREND",
      "symbol": "SPY",
      "signal": "hold",
      "price": 750.08,
      "atr": 9.9824,
      "qty": 0,
      "stop_price": null,
      "tp_price": null,
      "executed": false,
      "skip_reason": "no_signal",
      "order_id": null,
      "vix": 15.89,
      "vix_reason": "vix_clear",
      "indicators": {
        "ema_fast": 743.65,
        "ema_mid": 741.96,
        "ema_slow": 730.93
      }
    },
    {
      "timestamp": "2026-07-06T13:45:27.337396-04:00",
      "strategy": "triple_ema",
      "strategy_type": "daily",
      "vix_type": "TREND",
      "symbol": "QQQ",
      "signal": "hold",
      "price": 721.62,
      "atr": 16.8119,
      "qty": 0,
      "stop_price": null,
      "tp_price": null,
      "executed": false,
      "skip_reason": "no_signal",
      "order_id": null,
      "vix": 15.89,
      "vix_reason": "vix_clear",
      "indicators": {
        "ema_fast": 721.19,
        "ema_mid": 720.48,
        "ema_slow": 699.96
      }
    },
    {
      "timestamp": "2026-07-06T13:45:27.337396-04:00",
      "strategy": "triple_ema",
      "strategy_type": "daily",
      "vix_type": "TREND",
      "symbol": "IWM",
      "signal": "hold",
      "price": 299.53,
      "atr": 4.93,
      "qty": 0,
      "stop_price": null,
      "tp_price": null,
      "executed": false,
      "skip_reason": "no_signal",
      "order_id": null,
      "vix": 15.89,
      "vix_reason": "vix_clear",
      "indicators": {
        "ema_fast": 298.13,
        "ema_mid": 294.43,
        "ema_slow": 285.41
      }
    },
    {
      "timestamp": "2026-07-06T13:45:27.337396-04:00",
      "strategy": "triple_ema",
      "strategy_type": "daily",
      "vix_type": "TREND",
      "symbol": "GLD",
      "signal": "hold",
      "price": 381.56,
      "atr": 7.467,
      "qty": 0,
      "stop_price": null,
      "tp_price": null,
      "executed": false,
      "skip_reason": "no_signal",
      "order_id": null,
      "vix": 15.89,
      "vix_reason": "vix_clear",
      "indicators": {
        "ema_fast": 376.17,
        "ema_mid": 384.23,
        "ema_slow": 402.27
      }
    },
    {
      "timestamp": "2026-07-06T13:45:27.337396-04:00",
      "strategy": "triple_ema",
      "strategy_type": "daily",
      "vix_type": "TREND",
      "symbol": "XLK",
      "signal": "hold",
      "price": 183.5,
      "atr": 6.163,
      "qty": 0,
      "stop_price": null,
      "tp_price": null,
      "executed": false,
      "skip_reason": "no_signal",
      "order_id": null,
      "vix": 15.89,
      "vix_reason": "vix_clear",
      "indicators": {
        "ema_fast": 184.53,
        "ema_mid": 184.47,
        "ema_slow": 176.85
      }
    },
    {
      "timestamp": "2026-07-06T13:45:27.337396-04:00",
      "strategy": "triple_ema",
      "strategy_type": "daily",
      "vix_type": "TREND",
      "symbol": "XLE",
      "signal": "hold",
      "price": 53.28,
      "atr": 0.9638,
      "qty": 0,
      "stop_price": null,
      "tp_price": null,
      "executed": false,
      "skip_reason": "no_signal",
      "order_id": null,
      "vix": 15.89,
      "vix_reason": "vix_clear",
      "indicators": {
        "ema_fast": 53.56,
        "ema_mid": 54.82,
        "ema_slow": 56.27
      }
    },
    {
      "timestamp": "2026-07-06T13:45:27.337396-04:00",
      "strategy": "triple_ema",
      "strategy_type": "daily",
      "vix_type": "TREND",
      "symbol": "XLF",
      "signal": "hold",
      "price": 56.02,
      "atr": 0.7587,
      "qty": 0,
      "stop_price": null,
      "tp_price": null,
      "executed": false,
      "skip_reason": "no_signal",
      "order_id": null,
      "vix": 15.89,
      "vix_reason": "vix_clear",
      "indicators": {
        "ema_fast": 54.64,
        "ema_mid": 53.69,
        "ema_slow": 52.67
      }
    },
    {
      "timestamp": "2026-07-06T13:45:27.337396-04:00",
      "strategy": "triple_ema",
      "strategy_type": "daily",
      "vix_type": "TREND",
      "symbol": "PANW",
      "signal": "hold",
      "price": 356.49,
      "atr": 15.8366,
      "qty": 0,
      "stop_price": null,
      "tp_price": null,
      "executed": false,
      "skip_reason": "no_signal",
      "order_id": null,
      "vix": 15.89,
      "vix_reason": "vix_clear",
      "indicators": {
        "ema_fast": 331.81,
        "ema_mid": 303.28,
        "ema_slow": 260.29
      }
    },
    {
      "timestamp": "2026-07-06T13:45:27.337396-04:00",
      "strategy": "triple_ema",
      "strategy_type": "daily",
      "vix_type": "TREND",
      "symbol": "INTC",
      "signal": "hold",
      "price": 122.73,
      "atr": 10.7135,
      "qty": 0,
      "stop_price": null,
      "tp_price": null,
      "executed": false,
      "skip_reason": "no_signal",
      "order_id": null,
      "vix": 15.89,
      "vix_reason": "vix_clear",
      "indicators": {
        "ema_fast": 127.17,
        "ema_mid": 124.14,
        "ema_slow": 108.65
      }
    },
    {
      "timestamp": "2026-07-06T13:45:27.337396-04:00",
      "strategy": "triple_ema",
      "strategy_type": "daily",
      "vix_type": "TREND",
      "symbol": "AMD",
      "signal": "hold",
      "price": 553.72,
      "atr": 40.0685,
      "qty": 0,
      "stop_price": null,
      "tp_price": null,
      "executed": false,
      "skip_reason": "no_signal",
      "order_id": null,
      "vix": 15.89,
      "vix_reason": "vix_clear",
      "indicators": {
        "ema_fast": 538.66,
        "ema_mid": 519.67,
        "ema_slow": 451.64
      }
    },
    {
      "timestamp": "2026-07-06T13:45:27.337396-04:00",
      "strategy": "triple_ema",
      "strategy_type": "daily",
      "vix_type": "TREND",
      "symbol": "MRVL",
      "signal": "hold",
      "price": 249.43,
      "atr": 26.7322,
      "qty": 0,
      "stop_price": null,
      "tp_price": null,
      "executed": false,
      "skip_reason": "no_signal",
      "order_id": null,
      "vix": 15.89,
      "vix_reason": "vix_clear",
      "indicators": {
        "ema_fast": 268.17,
        "ema_mid": 266.48,
        "ema_slow": 225.11
      }
    },
    {
      "timestamp": "2026-07-06T13:45:27.337396-04:00",
      "strategy": "triple_ema",
      "strategy_type": "daily",
      "vix_type": "TREND",
      "symbol": "HOOD",
      "signal": "hold",
      "price": 116.42,
      "atr": 7.1935,
      "qty": 0,
      "stop_price": null,
      "tp_price": null,
      "executed": false,
      "skip_reason": "no_signal",
      "order_id": null,
      "vix": 15.89,
      "vix_reason": "vix_clear",
      "indicators": {
        "ema_fast": 106.72,
        "ema_mid": 99.34,
        "ema_slow": 90.83
      }
    },
    {
      "timestamp": "2026-07-06T13:45:27.337396-04:00",
      "strategy": "triple_ema",
      "strategy_type": "daily",
      "vix_type": "TREND",
      "symbol": "AMAT",
      "signal": "hold",
      "price": 593.32,
      "atr": 53.77,
      "qty": 0,
      "stop_price": null,
      "tp_price": null,
      "executed": false,
      "skip_reason": "no_signal",
      "order_id": null,
      "vix": 15.89,
      "vix_reason": "vix_clear",
      "indicators": {
        "ema_fast": 628.63,
        "ema_mid": 589.76,
        "ema_slow": 508.83
      }
    },
    {
      "timestamp": "2026-07-06T13:45:27.337396-04:00",
      "strategy": "triple_ema",
      "strategy_type": "daily",
      "vix_type": "TREND",
      "symbol": "SNOW",
      "signal": "hold",
      "price": 262.41,
      "atr": 12.0725,
      "qty": 0,
      "stop_price": null,
      "tp_price": null,
      "executed": false,
      "skip_reason": "no_signal",
      "order_id": null,
      "vix": 15.89,
      "vix_reason": "vix_clear",
      "indicators": {
        "ema_fast": 252.17,
        "ema_mid": 238.63,
        "ema_slow": 211.65
      }
    },
    {
      "timestamp": "2026-07-06T13:45:27.337396-04:00",
      "strategy": "triple_ema",
      "strategy_type": "daily",
      "vix_type": "TREND",
      "symbol": "LRCX",
      "signal": "hold",
      "price": 350.99,
      "atr": 31.0764,
      "qty": 0,
      "stop_price": null,
      "tp_price": null,
      "executed": false,
      "skip_reason": "no_signal",
      "order_id": null,
      "vix": 15.89,
      "vix_reason": "vix_clear",
      "indicators": {
        "ema_fast": 378.25,
        "ema_mid": 367.19,
        "ema_slow": 326.75
      }
    },
    {
      "timestamp": "2026-07-06T13:45:27.337396-04:00",
      "strategy": "triple_ema",
      "strategy_type": "daily",
      "vix_type": "TREND",
      "symbol": "BAC",
      "signal": "hold",
      "price": 59.72,
      "atr": 1.1708,
      "qty": 0,
      "stop_price": null,
      "tp_price": null,
      "executed": false,
      "skip_reason": "no_signal",
      "order_id": null,
      "vix": 15.89,
      "vix_reason": "vix_clear",
      "indicators": {
        "ema_fast": 58.21,
        "ema_mid": 56.63,
        "ema_slow": 54.4
      }
    },
    {
      "timestamp": "2026-07-06T13:45:27.337396-04:00",
      "strategy": "triple_ema",
      "strategy_type": "daily",
      "vix_type": "TREND",
      "symbol": "V",
      "signal": "hold",
      "price": 356.82,
      "atr": 9.2199,
      "qty": 0,
      "stop_price": null,
      "tp_price": null,
      "executed": false,
      "skip_reason": "no_signal",
      "order_id": null,
      "vix": 15.89,
      "vix_reason": "vix_clear",
      "indicators": {
        "ema_fast": 346.6,
        "ema_mid": 336.36,
        "ema_slow": 327.87
      }
    },
    {
      "timestamp": "2026-07-06T13:45:27.337396-04:00",
      "strategy": "triple_ema",
      "strategy_type": "daily",
      "vix_type": "TREND",
      "symbol": "MS",
      "signal": "hold",
      "price": 220.29,
      "atr": 5.9163,
      "qty": 0,
      "stop_price": null,
      "tp_price": null,
      "executed": false,
      "skip_reason": "no_signal",
      "order_id": null,
      "vix": 15.89,
      "vix_reason": "vix_clear",
      "indicators": {
        "ema_fast": 215.85,
        "ema_mid": 214.3,
        "ema_slow": 203.93
      }
    },
    {
      "timestamp": "2026-07-06T13:45:27.337396-04:00",
      "strategy": "triple_ema",
      "strategy_type": "daily",
      "vix_type": "TREND",
      "symbol": "SOFI",
      "signal": "hold",
      "price": 18.68,
      "atr": 0.9413,
      "qty": 0,
      "stop_price": null,
      "tp_price": null,
      "executed": false,
      "skip_reason": "no_signal",
      "order_id": null,
      "vix": 15.89,
      "vix_reason": "vix_clear",
      "indicators": {
        "ema_fast": 18.09,
        "ema_mid": 17.56,
        "ema_slow": 17.42
      }
    },
    {
      "timestamp": "2026-07-06T13:45:27.337396-04:00",
      "strategy": "triple_ema",
      "strategy_type": "daily",
      "vix_type": "TREND",
      "symbol": "XLV",
      "signal": "hold",
      "price": 162.15,
      "atr": 2.8515,
      "qty": 0,
      "stop_price": null,
      "tp_price": null,
      "executed": false,
      "skip_reason": "no_signal",
      "order_id": null,
      "vix": 15.89,
      "vix_reason": "vix_clear",
      "indicators": {
        "ema_fast": 159.41,
        "ema_mid": 155.58,
        "ema_slow": 152.03
      }
    },
    {
      "timestamp": "2026-07-06T13:45:27.337396-04:00",
      "strategy": "triple_ema",
      "strategy_type": "daily",
      "vix_type": "TREND",
      "symbol": "MRK",
      "signal": "hold",
      "price": 126.73,
      "atr": 3.5509,
      "qty": 0,
      "stop_price": null,
      "tp_price": null,
      "executed": false,
      "skip_reason": "no_signal",
      "order_id": null,
      "vix": 15.89,
      "vix_reason": "vix_clear",
      "indicators": {
        "ema_fast": 125.92,
        "ema_mid": 122.33,
        "ema_slow": 118.9
      }
    },
    {
      "timestamp": "2026-07-06T13:45:27.337396-04:00",
      "strategy": "triple_ema",
      "strategy_type": "daily",
      "vix_type": "TREND",
      "symbol": "XLY",
      "signal": "hold",
      "price": 117.78,
      "atr": 2.21,
      "qty": 0,
      "stop_price": null,
      "tp_price": null,
      "executed": false,
      "skip_reason": "no_signal",
      "order_id": null,
      "vix": 15.89,
      "vix_reason": "vix_clear",
      "indicators": {
        "ema_fast": 116.8,
        "ema_mid": 116.61,
        "ema_slow": 117.3
      }
    },
    {
      "timestamp": "2026-07-06T13:45:27.337396-04:00",
      "strategy": "triple_ema",
      "strategy_type": "daily",
      "vix_type": "TREND",
      "symbol": "XLI",
      "signal": "hold",
      "price": 185.33,
      "atr": 3.2069,
      "qty": 0,
      "stop_price": null,
      "tp_price": null,
      "executed": false,
      "skip_reason": "no_signal",
      "order_id": null,
      "vix": 15.89,
      "vix_reason": "vix_clear",
      "indicators": {
        "ema_fast": 183.19,
        "ema_mid": 180.15,
        "ema_slow": 175.93
      }
    },
    {
      "timestamp": "2026-07-06T13:45:27.337396-04:00",
      "strategy": "triple_ema",
      "strategy_type": "daily",
      "vix_type": "TREND",
      "symbol": "ARKK",
      "signal": "hold",
      "price": 83.4,
      "atr": 2.6954,
      "qty": 0,
      "stop_price": null,
      "tp_price": null,
      "executed": false,
      "skip_reason": "no_signal",
      "order_id": null,
      "vix": 15.89,
      "vix_reason": "vix_clear",
      "indicators": {
        "ema_fast": 80.65,
        "ema_mid": 79.07,
        "ema_slow": 77.47
      }
    },
    {
      "timestamp": "2026-07-06T13:45:27.337396-04:00",
      "strategy": "triple_ema",
      "strategy_type": "daily",
      "vix_type": "TREND",
      "symbol": "DIS",
      "signal": "hold",
      "price": 97.59,
      "atr": 2.4861,
      "qty": 0,
      "stop_price": null,
      "tp_price": null,
      "executed": false,
      "skip_reason": "no_signal",
      "order_id": null,
      "vix": 15.89,
      "vix_reason": "vix_clear",
      "indicators": {
        "ema_fast": 98.44,
        "ema_mid": 99.79,
        "ema_slow": 101.24
      }
    },
    {
      "timestamp": "2026-07-06T13:45:27.337396-04:00",
      "strategy": "triple_ema",
      "strategy_type": "daily",
      "vix_type": "TREND",
      "symbol": "GOOGL",
      "signal": "hold",
      "price": 364.46,
      "atr": 10.918,
      "qty": 0,
      "stop_price": null,
      "tp_price": null,
      "executed": false,
      "skip_reason": "no_signal",
      "order_id": null,
      "vix": 15.89,
      "vix_reason": "vix_clear",
      "indicators": {
        "ema_fast": 357.25,
        "ema_mid": 359.71,
        "ema_slow": 357.86
      }
    },
    {
      "timestamp": "2026-07-06T13:45:27.337396-04:00",
      "strategy": "triple_ema",
      "strategy_type": "daily",
      "vix_type": "TREND",
      "symbol": "UBER",
      "signal": "hold",
      "price": 73.43,
      "atr": 2.7015,
      "qty": 0,
      "stop_price": null,
      "tp_price": null,
      "executed": false,
      "skip_reason": "no_signal",
      "order_id": null,
      "vix": 15.89,
      "vix_reason": "vix_clear",
      "indicators": {
        "ema_fast": 73.32,
        "ema_mid": 72.69,
        "ema_slow": 73.16
      }
    },
    {
      "timestamp": "2026-07-06T13:45:27.337396-04:00",
      "strategy": "ema_crossover",
      "strategy_type": "daily",
      "vix_type": "TREND",
      "symbol": "AAPL",
      "signal": "buy",
      "price": 312.4,
      "atr": 9.3796,
      "qty": 0,
      "stop_price": null,
      "tp_price": null,
      "executed": false,
      "skip_reason": "already_in_position",
      "order_id": null,
      "vix": 15.89,
      "vix_reason": "vix_clear",
      "indicators": {
        "ema_fast": 296.34,
        "ema_slow": 295.54,
        "diff": 0.7957
      }
    },
    {
      "timestamp": "2026-07-06T13:45:27.337396-04:00",
      "strategy": "ema_crossover",
      "strategy_type": "daily",
      "vix_type": "TREND",
      "symbol": "NKE",
      "signal": "hold",
      "price": 43.06,
      "atr": 1.6473,
      "qty": 0,
      "stop_price": null,
      "tp_price": null,
      "executed": false,
      "skip_reason": "no_signal",
      "order_id": null,
      "vix": 15.89,
      "vix_reason": "vix_clear",
      "indicators": {
        "ema_fast": 42.84,
        "ema_slow": 43.38,
        "diff": -0.5374
      }
    },
    {
      "timestamp": "2026-07-06T13:45:27.337396-04:00",
      "strategy": "ema_crossover",
      "strategy_type": "daily",
      "vix_type": "TREND",
      "symbol": "PYPL",
      "signal": "buy",
      "price": 44.96,
      "atr": 1.4627,
      "qty": 0,
      "stop_price": null,
      "tp_price": null,
      "executed": false,
      "skip_reason": "already_in_position",
      "order_id": null,
      "vix": 15.89,
      "vix_reason": "vix_clear",
      "indicators": {
        "ema_fast": 43.71,
        "ema_slow": 43.6,
        "diff": 0.1141
      }
    },
    {
      "timestamp": "2026-07-06T13:45:27.337396-04:00",
      "strategy": "ema_crossover",
      "strategy_type": "daily",
      "vix_type": "TREND",
      "symbol": "SPY",
      "signal": "hold",
      "price": 750.08,
      "atr": 9.9824,
      "qty": 0,
      "stop_price": null,
      "tp_price": null,
      "executed": false,
      "skip_reason": "no_signal",
      "order_id": null,
      "vix": 15.89,
      "vix_reason": "vix_clear",
      "indicators": {
        "ema_fast": 742.86,
        "ema_slow": 740.98,
        "diff": 1.875
      }
    },
    {
      "timestamp": "2026-07-06T13:45:27.337396-04:00",
      "strategy": "ema_crossover",
      "strategy_type": "daily",
      "vix_type": "TREND",
      "symbol": "QQQ",
      "signal": "hold",
      "price": 721.62,
      "atr": 16.8119,
      "qty": 0,
      "stop_price": null,
      "tp_price": null,
      "executed": false,
      "skip_reason": "no_signal",
      "order_id": null,
      "vix": 15.89,
      "vix_reason": "vix_clear",
      "indicators": {
        "ema_fast": 721.52,
        "ema_slow": 718.56,
        "diff": 2.9597
      }
    },
    {
      "timestamp": "2026-07-06T13:45:27.337396-04:00",
      "strategy": "ema_crossover",
      "strategy_type": "daily",
      "vix_type": "TREND",
      "symbol": "IWM",
      "signal": "hold",
      "price": 299.53,
      "atr": 4.93,
      "qty": 0,
      "stop_price": null,
      "tp_price": null,
      "executed": false,
      "skip_reason": "no_signal",
      "order_id": null,
      "vix": 15.89,
      "vix_reason": "vix_clear",
      "indicators": {
        "ema_fast": 297.02,
        "ema_slow": 293.01,
        "diff": 4.0105
      }
    },
    {
      "timestamp": "2026-07-06T13:45:27.337396-04:00",
      "strategy": "ema_crossover",
      "strategy_type": "daily",
      "vix_type": "TREND",
      "symbol": "GLD",
      "signal": "hold",
      "price": 381.56,
      "atr": 7.467,
      "qty": 0,
      "stop_price": null,
      "tp_price": null,
      "executed": false,
      "skip_reason": "no_signal",
      "order_id": null,
      "vix": 15.89,
      "vix_reason": "vix_clear",
      "indicators": {
        "ema_fast": 378.09,
        "ema_slow": 387.62,
        "diff": -9.5247
      }
    },
    {
      "timestamp": "2026-07-06T13:45:27.337396-04:00",
      "strategy": "ema_crossover",
      "strategy_type": "daily",
      "vix_type": "TREND",
      "symbol": "XLK",
      "signal": "hold",
      "price": 183.5,
      "atr": 6.163,
      "qty": 0,
      "stop_price": null,
      "tp_price": null,
      "executed": false,
      "skip_reason": "no_signal",
      "order_id": null,
      "vix": 15.89,
      "vix_reason": "vix_clear",
      "indicators": {
        "ema_fast": 184.89,
        "ema_slow": 183.63,
        "diff": 1.257
      }
    },
    {
      "timestamp": "2026-07-06T13:45:27.337396-04:00",
      "strategy": "ema_crossover",
      "strategy_type": "daily",
      "vix_type": "TREND",
      "symbol": "XLE",
      "signal": "hold",
      "price": 53.28,
      "atr": 0.9638,
      "qty": 0,
      "stop_price": null,
      "tp_price": null,
      "executed": false,
      "skip_reason": "no_signal",
      "order_id": null,
      "vix": 15.89,
      "vix_reason": "vix_clear",
      "indicators": {
        "ema_fast": 53.97,
        "ema_slow": 55.18,
        "diff": -1.2079
      }
    },
    {
      "timestamp": "2026-07-06T13:45:27.337396-04:00",
      "strategy": "ema_crossover",
      "strategy_type": "daily",
      "vix_type": "TREND",
      "symbol": "XLF",
      "signal": "hold",
      "price": 56.02,
      "atr": 0.7587,
      "qty": 0,
      "stop_price": null,
      "tp_price": null,
      "executed": false,
      "skip_reason": "no_signal",
      "order_id": null,
      "vix": 15.89,
      "vix_reason": "vix_clear",
      "indicators": {
        "ema_fast": 54.27,
        "ema_slow": 53.46,
        "diff": 0.8165
      }
    },
    {
      "timestamp": "2026-07-06T13:45:27.337396-04:00",
      "strategy": "ema_crossover",
      "strategy_type": "daily",
      "vix_type": "TREND",
      "symbol": "PANW",
      "signal": "hold",
      "price": 356.49,
      "atr": 15.8366,
      "qty": 0,
      "stop_price": null,
      "tp_price": null,
      "executed": false,
      "skip_reason": "no_signal",
      "order_id": null,
      "vix": 15.89,
      "vix_reason": "vix_clear",
      "indicators": {
        "ema_fast": 320.92,
        "ema_slow": 295.17,
        "diff": 25.7441
      }
    },
    {
      "timestamp": "2026-07-06T13:45:27.337396-04:00",
      "strategy": "ema_crossover",
      "strategy_type": "daily",
      "vix_type": "TREND",
      "symbol": "INTC",
      "signal": "hold",
      "price": 122.73,
      "atr": 10.7135,
      "qty": 0,
      "stop_price": null,
      "tp_price": null,
      "executed": false,
      "skip_reason": "no_signal",
      "order_id": null,
      "vix": 15.89,
      "vix_reason": "vix_clear",
      "indicators": {
        "ema_fast": 126.87,
        "ema_slow": 122.14,
        "diff": 4.7321
      }
    },
    {
      "timestamp": "2026-07-06T13:45:27.337396-04:00",
      "strategy": "ema_crossover",
      "strategy_type": "daily",
      "vix_type": "TREND",
      "symbol": "AMD",
      "signal": "hold",
      "price": 553.72,
      "atr": 40.0685,
      "qty": 0,
      "stop_price": null,
      "tp_price": null,
      "executed": false,
      "skip_reason": "no_signal",
      "order_id": null,
      "vix": 15.89,
      "vix_reason": "vix_clear",
      "indicators": {
        "ema_fast": 533.66,
        "ema_slow": 510.27,
        "diff": 23.3852
      }
    },
    {
      "timestamp": "2026-07-06T13:45:27.337396-04:00",
      "strategy": "ema_crossover",
      "strategy_type": "daily",
      "vix_type": "TREND",
      "symbol": "MRVL",
      "signal": "hold",
      "price": 249.43,
      "atr": 26.7322,
      "qty": 0,
      "stop_price": null,
      "tp_price": null,
      "executed": false,
      "skip_reason": "no_signal",
      "order_id": null,
      "vix": 15.89,
      "vix_reason": "vix_clear",
      "indicators": {
        "ema_fast": 271.05,
        "ema_slow": 260.97,
        "diff": 10.0869
      }
    },
    {
      "timestamp": "2026-07-06T13:45:27.337396-04:00",
      "strategy": "ema_crossover",
      "strategy_type": "daily",
      "vix_type": "TREND",
      "symbol": "HOOD",
      "signal": "hold",
      "price": 116.42,
      "atr": 7.1935,
      "qty": 0,
      "stop_price": null,
      "tp_price": null,
      "executed": false,
      "skip_reason": "no_signal",
      "order_id": null,
      "vix": 15.89,
      "vix_reason": "vix_clear",
      "indicators": {
        "ema_fast": 104.01,
        "ema_slow": 97.3,
        "diff": 6.7152
      }
    },
    {
      "timestamp": "2026-07-06T13:45:27.337396-04:00",
      "strategy": "ema_crossover",
      "strategy_type": "daily",
      "vix_type": "TREND",
      "symbol": "AMAT",
      "signal": "hold",
      "price": 593.32,
      "atr": 53.77,
      "qty": 0,
      "stop_price": null,
      "tp_price": null,
      "executed": false,
      "skip_reason": "no_signal",
      "order_id": null,
      "vix": 15.89,
      "vix_reason": "vix_clear",
      "indicators": {
        "ema_fast": 619.36,
        "ema_slow": 574.23,
        "diff": 45.1289
      }
    },
    {
      "timestamp": "2026-07-06T13:45:27.337396-04:00",
      "strategy": "ema_crossover",
      "strategy_type": "daily",
      "vix_type": "TREND",
      "symbol": "SNOW",
      "signal": "hold",
      "price": 262.41,
      "atr": 12.0725,
      "qty": 0,
      "stop_price": null,
      "tp_price": null,
      "executed": false,
      "skip_reason": "no_signal",
      "order_id": null,
      "vix": 15.89,
      "vix_reason": "vix_clear",
      "indicators": {
        "ema_fast": 247.75,
        "ema_slow": 233.49,
        "diff": 14.2694
      }
    },
    {
      "timestamp": "2026-07-06T13:45:27.337396-04:00",
      "strategy": "ema_crossover",
      "strategy_type": "daily",
      "vix_type": "TREND",
      "symbol": "LRCX",
      "signal": "hold",
      "price": 350.99,
      "atr": 31.0764,
      "qty": 0,
      "stop_price": null,
      "tp_price": null,
      "executed": false,
      "skip_reason": "no_signal",
      "order_id": null,
      "vix": 15.89,
      "vix_reason": "vix_clear",
      "indicators": {
        "ema_fast": 377.45,
        "ema_slow": 360.47,
        "diff": 16.976
      }
    },
    {
      "timestamp": "2026-07-06T13:45:27.337396-04:00",
      "strategy": "ema_crossover",
      "strategy_type": "daily",
      "vix_type": "TREND",
      "symbol": "BAC",
      "signal": "hold",
      "price": 59.72,
      "atr": 1.1708,
      "qty": 0,
      "stop_price": null,
      "tp_price": null,
      "executed": false,
      "skip_reason": "no_signal",
      "order_id": null,
      "vix": 15.89,
      "vix_reason": "vix_clear",
      "indicators": {
        "ema_fast": 57.7,
        "ema_slow": 56.14,
        "diff": 1.5574
      }
    },
    {
      "timestamp": "2026-07-06T13:45:27.337396-04:00",
      "strategy": "ema_crossover",
      "strategy_type": "daily",
      "vix_type": "TREND",
      "symbol": "V",
      "signal": "hold",
      "price": 356.82,
      "atr": 9.2199,
      "qty": 0,
      "stop_price": null,
      "tp_price": null,
      "executed": false,
      "skip_reason": "no_signal",
      "order_id": null,
      "vix": 15.89,
      "vix_reason": "vix_clear",
      "indicators": {
        "ema_fast": 342.17,
        "ema_slow": 334.29,
        "diff": 7.8779
      }
    },
    {
      "timestamp": "2026-07-06T13:45:27.337396-04:00",
      "strategy": "ema_crossover",
      "strategy_type": "daily",
      "vix_type": "TREND",
      "symbol": "MS",
      "signal": "hold",
      "price": 220.29,
      "atr": 5.9163,
      "qty": 0,
      "stop_price": null,
      "tp_price": null,
      "executed": false,
      "skip_reason": "no_signal",
      "order_id": null,
      "vix": 15.89,
      "vix_reason": "vix_clear",
      "indicators": {
        "ema_fast": 215.9,
        "ema_slow": 212.86,
        "diff": 3.0467
      }
    },
    {
      "timestamp": "2026-07-06T13:45:27.337396-04:00",
      "strategy": "ema_crossover",
      "strategy_type": "daily",
      "vix_type": "TREND",
      "symbol": "SOFI",
      "signal": "hold",
      "price": 18.68,
      "atr": 0.9413,
      "qty": 0,
      "stop_price": null,
      "tp_price": null,
      "executed": false,
      "skip_reason": "no_signal",
      "order_id": null,
      "vix": 15.89,
      "vix_reason": "vix_clear",
      "indicators": {
        "ema_fast": 17.88,
        "ema_slow": 17.44,
        "diff": 0.4341
      }
    },
    {
      "timestamp": "2026-07-06T13:45:27.337396-04:00",
      "strategy": "ema_crossover",
      "strategy_type": "daily",
      "vix_type": "TREND",
      "symbol": "XLV",
      "signal": "hold",
      "price": 162.15,
      "atr": 2.8515,
      "qty": 0,
      "stop_price": null,
      "tp_price": null,
      "executed": false,
      "skip_reason": "no_signal",
      "order_id": null,
      "vix": 15.89,
      "vix_reason": "vix_clear",
      "indicators": {
        "ema_fast": 157.91,
        "ema_slow": 154.66,
        "diff": 3.2407
      }
    },
    {
      "timestamp": "2026-07-06T13:45:27.337396-04:00",
      "strategy": "ema_crossover",
      "strategy_type": "daily",
      "vix_type": "TREND",
      "symbol": "MRK",
      "signal": "hold",
      "price": 126.73,
      "atr": 3.5509,
      "qty": 0,
      "stop_price": null,
      "tp_price": null,
      "executed": false,
      "skip_reason": "no_signal",
      "order_id": null,
      "vix": 15.89,
      "vix_reason": "vix_clear",
      "indicators": {
        "ema_fast": 124.52,
        "ema_slow": 121.5,
        "diff": 3.0152
      }
    },
    {
      "timestamp": "2026-07-06T13:45:27.337396-04:00",
      "strategy": "ema_crossover",
      "strategy_type": "daily",
      "vix_type": "TREND",
      "symbol": "XLY",
      "signal": "hold",
      "price": 117.78,
      "atr": 2.21,
      "qty": 0,
      "stop_price": null,
      "tp_price": null,
      "executed": false,
      "skip_reason": "no_signal",
      "order_id": null,
      "vix": 15.89,
      "vix_reason": "vix_clear",
      "indicators": {
        "ema_fast": 116.61,
        "ema_slow": 116.66,
        "diff": -0.0585
      }
    },
    {
      "timestamp": "2026-07-06T13:45:27.337396-04:00",
      "strategy": "ema_crossover",
      "strategy_type": "daily",
      "vix_type": "TREND",
      "symbol": "XLI",
      "signal": "hold",
      "price": 185.33,
      "atr": 3.2069,
      "qty": 0,
      "stop_price": null,
      "tp_price": null,
      "executed": false,
      "skip_reason": "no_signal",
      "order_id": null,
      "vix": 15.89,
      "vix_reason": "vix_clear",
      "indicators": {
        "ema_fast": 182.13,
        "ema_slow": 179.29,
        "diff": 2.8452
      }
    },
    {
      "timestamp": "2026-07-06T13:45:27.337396-04:00",
      "strategy": "ema_crossover",
      "strategy_type": "daily",
      "vix_type": "TREND",
      "symbol": "ARKK",
      "signal": "hold",
      "price": 83.4,
      "atr": 2.6954,
      "qty": 0,
      "stop_price": null,
      "tp_price": null,
      "executed": false,
      "skip_reason": "no_signal",
      "order_id": null,
      "vix": 15.89,
      "vix_reason": "vix_clear",
      "indicators": {
        "ema_fast": 79.94,
        "ema_slow": 78.74,
        "diff": 1.1945
      }
    },
    {
      "timestamp": "2026-07-06T13:45:27.337396-04:00",
      "strategy": "ema_crossover",
      "strategy_type": "daily",
      "vix_type": "TREND",
      "symbol": "DIS",
      "signal": "hold",
      "price": 97.59,
      "atr": 2.4861,
      "qty": 0,
      "stop_price": null,
      "tp_price": null,
      "executed": false,
      "skip_reason": "no_signal",
      "order_id": null,
      "vix": 15.89,
      "vix_reason": "vix_clear",
      "indicators": {
        "ema_fast": 98.96,
        "ema_slow": 100.12,
        "diff": -1.1539
      }
    },
    {
      "timestamp": "2026-07-06T13:45:27.337396-04:00",
      "strategy": "ema_crossover",
      "strategy_type": "daily",
      "vix_type": "TREND",
      "symbol": "GOOGL",
      "signal": "hold",
      "price": 364.46,
      "atr": 10.918,
      "qty": 0,
      "stop_price": null,
      "tp_price": null,
      "executed": false,
      "skip_reason": "no_signal",
      "order_id": null,
      "vix": 15.89,
      "vix_reason": "vix_clear",
      "indicators": {
        "ema_fast": 357.27,
        "ema_slow": 360.68,
        "diff": -3.4125
      }
    },
    {
      "timestamp": "2026-07-06T13:45:27.337396-04:00",
      "strategy": "ema_crossover",
      "strategy_type": "daily",
      "vix_type": "TREND",
      "symbol": "UBER",
      "signal": "hold",
      "price": 73.43,
      "atr": 2.7015,
      "qty": 0,
      "stop_price": null,
      "tp_price": null,
      "executed": false,
      "skip_reason": "no_signal",
      "order_id": null,
      "vix": 15.89,
      "vix_reason": "vix_clear",
      "indicators": {
        "ema_fast": 73.02,
        "ema_slow": 72.67,
        "diff": 0.3532
      }
    }
  ],
  "orders_placed": [],
  "trading_pnl": 204.15,
  "total_deposited": 27768.78,
  "deposit_count": 3,
  "ma20_bear_block": false,
  "ma20_spy_close": null,
  "ma20_value": null,
  "ma20_gap_pct": null,
  "regime_label": "BULL"
}